Workbook
Name ACTION: #REF!
Name ACTION: #REF!

Sheet Cover
B2: TEST REPORT DOCUMENT
A4: Project Name | B4: <Project Name> | E4: Creator
A5: Project Code | B5: <Project Code> | E5: Issue Date | F5: <Date when this test report is created>
A6: Document Code | B6: =B5&"_"&"XXX"&"_"&"vx.x" -> <Project Code>_XXX_vx.x | E6: Version
A9: Record of change
A10: Effective Date | B10: Version | C10: Change Item | D10: *A,D,M | E10: Change description | F10: Reference
A11: <Date when these changes are effective> | F11: <List of documents which are refered in this version.>

Sheet Test Cases
D1: TEST CASE LIST
B3: Project Name | D3: =#REF! -> #REF!
B4: Project Code | D4: =#REF! -> #REF!
B5: Test Environment Setup Description | D5: <List enviroment requires in this system 1. Server 2. Database 3. Web Browser ... >
B8: No | C8: Function Name | D8: Sheet Name | E8: Description | F8: Pre-Condition
B9: 1 | C9: Sign Up & Role Registration | D9: Sign Up & Role Registration
B10: 2 | C10: Sign In With Password | D10: Sign In
B11: 3 | C11: Forgot & Reset Password Flow | D11: Forgot & Reset Password Flow
B12: 4 | C12: Manage User Profile, Avatar & Settings | D12: Manage User Profile, Avatar & Settings
B13: 5 | C13: Identity Document Verification | D13: Identity Document Verification
B14: 6 | C14: Create Snake Catching Request (Images, GPS, Species) | D14: Create Snake Catching Request (Images, GPS, Species)
B15: 7 | C15: Process Catching Deposit (Round 1) | D15: Process Catching Deposit (Round 1)
B16: 8 | C16: Operator Verification & Assignment | D16: Operator Verification & Assignment
B17: 9 | C17: Rescuer EnRoute & Arrived Tracking | D17: Rescuer EnRoute & Arrived Tracking
B18: 10 | C18: Rescuer Mission Execution & Evidence Upload | D18: Rescuer Mission Execution & Evidence Upload
B19: 11 | C19: Process Actual Service Payment (Round 2) | D19: Process Actual Service Payment (Round 2)
B20: 12 | C20: Cancel Catching Request & Deposit Refund | D20: Cancel Catching Request & Deposit Refund
... B53: 45 | C53: Content: Blogs Database Management | D53: Content: Blogs Database Management

Sheet Test Statistics
B1: TEST STATISTICS
B3: Project Name | C3: <Project Name> | E3: Creator
B4: Project Code | C4: <Project Code> | E4: Reviewer/Approver
B5: Document Code | C5: =C4&"_"&"Test Report"&"_"&"vx.x" -> <Project Code>_Test Report_vx.x | E5: Issue Date | H5: <Date when this test report is created>
B6: Notes | C6: <List modules included in this release> ex: Release 1 includes 2 modules: Module1 and Module2
B10: No | C10: Module code | D10: Passed | E10: Failed | F10: Pending | G10: N/A | H10: Number of test cases
B11: 1 | C11: Sign Up & Role Registration | D11: ='Sign Up & Role Registration'!B6 -> 7 | E11: 0 | F11: 0 | G11: 0 | H11: ='Sign Up & Role Registration'!B4 -> 7
B12: 2 | C12: Sign In | D12: ='Sign In'!B6 -> 9 | E12: 0 | F12: 0 | G12: 0 | H12: ='Sign In'!B4 -> 9
B13: 3 | C13: Forgot & Reset Password Flow | D13: ='Forgot & Reset Password Flow'!B6 -> 5 | E13: 0 | F13: 0 | G13: 0 | H13: ='Forgot & Reset Password Flow'!B4 -> 5
B14: 4 | C14: Manage User Profile, Avatar & Settings | D14: ='Manage User Profile, Avatar & S'!B6 -> 7 | E14: 0 | F14: 0 | G14: 0 | H14: ='Manage User Profile, Avatar & S'!B4 -> 7
B15: 5 | C15: Identity Document Verification | D15: ='Identity Document Verification'!B6 -> 7 | E15: 0 | F15: 0 | G15: 0 | H15: ='Identity Document Verification'!B4 -> 7
B16: 6 | C16: Create Snake Catching Request (Images, GPS, Species) | D16: ='Create Snake Catching Request'!B6 -> 8 | E16: 0 | F16: 0 | G16: 0 | H16: ='Create Snake Catching Request'!B4 -> 8
B17: 7 | C17: Process Catching Deposit (Round 1) | D17: ='Process Catching Deposit (Round'!B6 -> 8 | E17: 0 | F17: 0 | G17: 0 | H17: ='Process Catching Deposit (Round'!B4 -> 8
B18: 8 | C18: Operator Verification & Assignment | D18: ='Operator Verification & Assignm'!B6 -> 6 | E18: 0 | F18: 0 | G18: 0 | H18: ='Operator Verification & Assignm'!B4 -> 6
B19: 9 | C19: Rescuer EnRoute & Arrived Tracking | D19: ='Rescuer EnRoute & Arrived Track'!B6 -> 6 | E19: 0 | F19: 0 | G19: 0 | H19: ='Rescuer EnRoute & Arrived Track'!B4 -> 6
B20: 10 | C20: Rescuer Mission Execution & Evidence Upload | D20: 0 | E20: 0 | F20: 0 | G20: 0 | H20: 0
B21: 11 | C21: Process Actual Service Payment (Round 2) | D21: 0 | E21: 0 | F21: 0 | G21: 0 | H21: 0
B22: 12 | C22: Cancel Catching Request & Deposit Refund | D22: 0 | E22: 0 | F22: 0 | G22: 0 | H22: 0
B23: 13 | C23: Trigger SOS Alarm (GPS, Symptoms, AI check) | D23: 0 | E23: 0 | F23: 0 | G23: 0 | H23: 0
B24: 14 | C24: Operator Fast-Track Verification & Assignment | D24: 0 | E24: 0 | F24: 0 | G24: 0 | H24: 0
B25: 15 | C25: Rescuer On-Scene Navigation & AI Triage | D25: 0 | E25: 0 | F25: 0 | G25: 0 | H25: 0
B26: 16 | C26: SOS Find Nearest Hospital (Navigation) | D26: 0 | E26: 0 | F26: 0 | G26: 0 | H26: 0
B27: 17 | C27: Process SOS Post-Service Payment | D27: 0 | E27: 0 | F27: 0 | G27: 0 | H27: 0
B28: 18 | C28: View & Filter Expert Directory | D28: ='View & Filter Expert Directory'!B6 -> 5 | E28: 0 | F28: 0 | G28: 0 | H28: 5
B29: 19 | C29: Book Instant Consultation | D29: ='Book Instant Consultation'!B6 -> 5 | E29: 0 | F29: 0 | G29: 0 | H29: 5
B30: 20 | C30: Book Scheduled Consultation | D30: ='Book Scheduled Consultation'!B6 -> 5 | E30: 0 | F30: 0 | G30: 0 | H30: 5
B31: 21 | C31: Process Consultation Escrow Payment | D31: ='Process Consultation Escrow Pay'!B6 -> 6 | E31: 0 | F31: 0 | G31: 0 | H31: 6
B32: 22 | C32: WebRTC Video Room & Waiting Room Logic | D32: 5 | E32: 0 | F32: 0 | G32: 0 | H32: 5
B33: 23 | C33: Cancellation & Escrow Refund Handling | D33: ='Cancellation & Escrow Refund Ha'!B6 -> 4 | E33: 0 | F33: 0 | G33: 0 | H33: 4
B34: 24 | C34: Read Community Blog & Safety Alerts | D34: 0 | E34: 0 | F34: 0 | G34: 0 | H34: 0
B35: 25 | C35: Manage Blog Posts (Admin/Operator) | D35: 0 | E35: 0 | F35: 0 | G35: 0 | H35: 0
B36: 26 | C36: Search & View Snake Library (Encyclopedia) | D36: 0 | E36: 0 | F36: 0 | G36: 0 | H36: 0
B37: 27 | C37: Search & View First Aid Protocol Guides | D37: 0 | E37: 0 | F37: 0 | G37: 0 | H37: 0
B38: 28 | C38: Access Rescuer Training Lessons | D38: 0 | E38: 0 | F38: 0 | G38: 0 | H38: 0
B39: 29 | C39: Manage SnakeAidPay Wallet (Top-up, History, Withdraw) | D39: 0 | E39: 0 | F39: 0 | G39: 0 | H39: 0
B40: 30 | C40: External Payment Interface (PayOS Callback) | D40: 0 | E40: 0 | F40: 0 | G40: 0 | H40: 0
B41: 31 | C41: Notification Tab & SignalR Broadcasts | D41: 0 | E41: 0 | F41: 0 | G41: 0 | H41: 0
B42: 32 | C42: Submit Ratings & Read Feedback | D42: 0 | E42: 0 | F42: 0 | G42: 0 | H42: 0
B43: 33 | C43: View Mission & Consultation History (Filtering, Detail) | D43: 0 | E43: 0 | F43: 0 | G43: 0 | H43: 0
B44: 34 | C44: Operator Dashboard & Admin Dashboard | D44: ='Operator Dashboard & Admin Dash'!B6 -> 13 | E44: 0 | F44: 0 | G44: 0 | H44: 13
B45: 35 | C45: Staff Workshifts Management | D45: ='Staff Workshifts Management'!B6 -> 12 | E45: 0 | F45: 0 | G45: 0 | H45: 12
B46: 36 | C46: Users Account & Role Management | D46: ='Users Account & Role Management'!B6 -> 7 | E46: 0 | F46: 0 | G46: 0 | H46: 7
B47: 37 | C47: Request Management | D47: ='Request Management'!B6 -> 19 | E47: 0 | F47: 0 | G47: 0 | H47: 19
B48: 38 | C48: Snakes Species Management | D48: ='Snakes Species Management'!B6 -> 10 | E48: 0 | F48: 0 | G48: 0 | H48: 10
B49: 39 | C49: Antivenoms Inventory & Management | D49: ='Antivenoms Inventory & Manageme'!B6 -> 6 | E49: 0 | F49: 0 | G49: 0 | H49: 6
B50: 40 | C50: Treatment Facilities Database Management | D50: ='Treatment Facilities Database M'!B6 -> 8 | E50: 0 | F50: 0 | G50: 0 | H50: 8
B51: 41 | C51: Finance: Transactions & Withdrawals Management | D51: ='Finance Transactions & Withdraw'!B6 -> 12 | E51: 0 | F51: 0 | G51: 0 | H51: 12
B52: 42 | C52: Report Media Management | D52: ='Report Media Management'!B6 -> 5 | E52: 0 | F52: 0 | G52: 0 | H52: 5
B53: 43 | C53: Portal System Settings & Configuration | D53: ='Portal System Settings & Config'!B6 -> 11 | E53: 0 | F53: 0 | G53: 0 | H53: 11
B54: 44 | C54: Learning: Lessons Database Management | D54: ='Learning Lessons Database Manag'!B6 -> 8 | E54: 0 | F54: 0 | G54: 0 | H54: 8
B55: 45 | C55: Content: Blogs Database Management | D55: ='Content Blogs Database Manageme'!B6 -> 12 | E55: 0 | F55: 0 | G55: 0 | H55: 12
C57: Sub total | D57: =SUM(D9:D56) -> 216 | E57: =SUM(E9:E56) -> 0 | F57: =SUM(F9:F56) -> 0 | G57: =SUM(G9:G56) -> 0 | H57: =SUM(H9:H56) -> 216
C59: Test coverage | E59: =(D57+E57)*100/(H57-G57) -> 100 | F59: %
C60: Test successful coverage | E60: =D57*100/(H57-G57) -> 100 | F60: %

Sheet Sign Up & Role Registration
A2: Feature | B2: Sign Up & Role Registration | R2: Passed
A3: Test requirement | B3: Register using email/password with profile data, accept required terms, complete OTP verification, and continue through role-specific onboarding. | R3: Failed
A4: Number of TCs | B4: =COUNTA(A12:A997) -> 7 | R4: Pending
A5: Testing Round | B5: Passed | C5: Failed | D5: Pending | E5: N/A | R5: N/A
A6: Round 1 | B6: =COUNTIF($F10:$F995,B5) -> 7 | C6: =COUNTIF($F10:$F995,C5) -> 0 | D6: =COUNTIF($F10:$F995,D5) -> 0 | E6: =COUNTIF($F10:$F995,E5) -> 0
A7: Round 2 | B7: =COUNTIF($I10:$I995,B5) -> 7 | C7: =COUNTIF($I10:$I995,C5) -> 0 | D7: =COUNTIF($I10:$I995,D5) -> 0 | E7: =COUNTIF($I10:$I995,E5) -> 0
A8: Round 3 | B8: =COUNTIF($L10:$L995,B5) -> 7 | C8: =COUNTIF($L10:$L995,C5) -> 0 | D8: =COUNTIF($L10:$L995,D5) -> 0 | E8: =COUNTIF($L10:$L991,E5) -> 0
A10: Test Case ID | B10: Test Case Description | C10: Test Case Procedure | D10: Expected Results | E10: Pre-conditions | F10: Round 1 | G10: Test date | H10: Tester | I10: Round 2 | J10: Test date | K10: Tester | L10: Round 3 | M10: Test date | N10: Tester | O10: Note
A11: Sign Up & Role Registration
A12: TC101 | B12: Successful Member sign-up with valid required data | C12: 1. Open the app and select the Member role card "Người Dùng". 2. On the login screen, click "Đăng ký ngay". 3. Enter valid values for all required fields. 4. Click "Đăng Ký". | D12: The system shows "Đăng ký thành công! Mã OTP đã được gửi đến email của bạn" and navigates to OTP verification. | E12: Authentication backend is available; email is not registered. | F12: Passed | H12: KhoaPA | I12: Passed | K12: TrungDN | L12: Passed | N12: DuongNM
A13: TC102 | B13: Expert registration follows approval workflow correctly | C13: 1. Open the app and select the Expert role card "Chuyên Gia". 2. On the login screen, click "Đăng ký ngay" and complete required fields. 3. Click "Tiếp Tục" to submit registration. 4. On "Xác Thực OTP" screen, enter a valid 6-digit code. 5. Continue to the pending approval flow and document submission step "Nộp Chứng Chỉ" according to the configured Expert onboarding route. | D13: Expert account is not considered fully verified until OTP succeeds; after successful OTP, user proceeds to pending/document onboarding flow. | E13: Expert approval workflow is enabled; email is not registered; OTP delivery is available. | F13: Passed | H13: KhoaPA | I13: Passed | K13: TrungDN | L13: Passed | N13: DuongNM
A14: TC103 | B14: OTP verification succeeds with a valid 6-digit code | C14: 1. Complete a new registration flow until the "Xác Thực OTP" screen appears. 2. Enter a valid 6-digit OTP. 3. Click "Xác Nhận". | D14: Verification succeeds and user moves to the next step. | E14: A newly registered account exists; valid OTP has been sent to email. | F14: Passed | H14: KhoaPA | I14: Passed | K14: TrungDN | L14: Passed | N14: DuongNM
A15: TC104 | B15: OTP verification is blocked for invalid or incomplete code | C15: 1. Open "Xác Thực OTP" screen. 2. Enter fewer than 6 digits or an invalid code. 3. Click "Xác Nhận". | D15: App shows validation or verification error (for example "Vui lòng nhập đủ 6 số") and stays on OTP screen. | E15: OTP screen is reachable from registration flow. | F15: Passed | H15: KhoaPA | I15: Passed | K15: TrungDN | L15: Passed | N15: DuongNM
A16: TC105 | B16: Required-field validation blocks incomplete sign-up | C16: 1. Open the Member registration screen or the Expert registration screen. 2. Leave at least one required field empty (for example, Email). 3. Submit with the role-specific primary action: Member clicks "Đăng Ký", Expert clicks "Tiếp Tục". | D16: Form submission is blocked and validation errors are displayed at missing fields. | E16: Registration screen is loaded successfully. | F16: Passed | H16: KhoaPA | I16: Passed | K16: TrungDN | L16: Passed | N16: DuongNM
A17: TC106 | B17: Weak password validation is enforced | C17: 1. Open the Member registration screen or the Expert registration screen. 2. Enter a weak password (too short or missing uppercase/digit). 3. Submit with the role-specific primary action: Member clicks "Đăng Ký", Expert clicks "Tiếp Tục". | D17: Validation error is shown (for example "Mật khẩu phải có ít nhất 1 chữ viết hoa" / "Mật khẩu phải có ít nhất 1 chữ số"); account is not created. | E17: Password policy is active. | F17: Passed | H17: KhoaPA | I17: Passed | K17: TrungDN | L17: Passed | N17: DuongNM
A18: TC107 | B18: Confirm-password mismatch is rejected | C18: 1. Open the Member registration screen or the Expert registration screen. 2. Enter different values for password and confirm password. 3. Submit with the role-specific primary action: Member clicks "Đăng Ký", Expert clicks "Tiếp Tục". | D18: The error "Mật khẩu không khớp" is shown and registration request is not sent. | E18: Registration screen is functioning normally. | F18: Passed | H18: KhoaPA | I18: Passed | K18: TrungDN | L18: Passed | N18: DuongNM

Sheet Sign In
A2: Feature | B2: Sign In | R2: Passed
A3: Test requirement | B3: Sign in using email/password for all roles, enforce required-field validation and role matching, and support remember-login behavior. | R3: Failed
A4: Number of TCs | B4: =COUNTA(A12:A995) -> 9 | R4: Pending
A5: Testing Round | B5: Passed | C5: Failed | D5: Pending | E5: N/A | R5: N/A
A6: Round 1 | B6: =COUNTIF($F10:$F993,B5) -> 9 | C6: =COUNTIF($F10:$F993,C5) -> 0 | D6: =COUNTIF($F10:$F993,D5) -> 0 | E6: =COUNTIF($F10:$F993,E5) -> 0
A7: Round 2 | B7: =COUNTIF($I10:$I993,B5) -> 9 | C7: =COUNTIF($I10:$I993,C5) -> 0 | D7: =COUNTIF($I10:$I993,D5) -> 0 | E7: =COUNTIF($I10:$I993,E5) -> 0
A8: Round 3 | B8: =COUNTIF($L10:$L993,B5) -> 9 | C8: =COUNTIF($L10:$L993,C5) -> 0 | D8: =COUNTIF($L10:$L993,D5) -> 0 | E8: =COUNTIF($L10:$L991,E5) -> 0
A10: Test Case ID | B10: Test Case Description | C10: Test Case Procedure | D10: Expected Results | E10: Pre-conditions | F10: Round 1 | G10: Test date | H10: Tester | I10: Round 2 | J10: Test date | K10: Tester | L10: Round 3 | M10: Test date | N10: Tester | O10: Note
A11: Sign In
A12: TC201 | B12: Member signs in successfully with valid credentials | C12: 1. Open the app and select Member role "Người Dùng". 2. Enter valid Email and Password. 3. Click "Đăng Nhập". | D12: The system shows "Đăng nhập thành công! Chào mừng [Tên]" and navigates to Member home screen. | E12: Member account exists and is active. | F12: Passed | H12: KhoaPA | I12: Passed | K12: TrungDN | L12: Passed | N12: DuongNM
A13: TC202 | B13: Expert signs in successfully with valid credentials | C13: 1. Open the app and select Expert role "Chuyên Gia". 2. Enter valid Email and Password. 3. Click "Đăng Nhập". | D13: Login succeeds and user is navigated to Expert home screen. | E13: Expert account is approved and active. | F13: Passed | H13: KhoaPA | I13: Passed | K13: TrungDN | L13: Passed | N13: DuongNM
A14: TC203 | B14: Rescuer signs in successfully with valid credentials | C14: 1. Open the app and select Rescuer role "Người Cứu Hộ". 2. Enter valid Email and Password. 3. Click "Đăng Nhập". | D14: Login succeeds and user is navigated to Rescuer home screen. | E14: Rescuer account exists and is active. | F14: Passed | H14: KhoaPA | I14: Passed | K14: TrungDN | L14: Passed | N14: DuongNM
A15: TC204 | B15: Role mismatch is blocked at login | C15: 1. Open Expert login screen. 2. Try to sign in with a Member account. 3. Click "Đăng Nhập". | D15: The system shows "Tài khoản này không phải là Expert. Vui lòng chọn đúng role khi đăng nhập." and blocks access. | E15: A valid Member account is available. | F15: Passed | H15: KhoaPA | I15: Passed | K15: TrungDN | L15: Passed | N15: DuongNM
A16: TC205 | B16: Required-field validation on login is enforced | C16: 1. Open any role login screen. 2. Leave Email or Password empty. 3. Click "Đăng Nhập". | D16: Validation errors are shown and login request is not sent. | E16: Login screen loads successfully. | F16: Passed | H16: KhoaPA | I16: Passed | K16: TrungDN | L16: Passed | N16: DuongNM
A17: TC206 | B17: Admin logs in successfully with valid credentials | C17: 1. Open web login page. 2. Select role Admin. 3. Enter valid Admin email and password. 4. Click "Đăng nhập". | D17: Login succeeds and user is redirected to Admin home/dashboard page. | E17: Active Admin account exists. | F17: Passed | H17: KhoaPA | I17: Passed | K17: DuongNM | L17: Passed | N17: KhoaPA
A18: TC207 | B18: Operator logs in successfully with valid credentials | C18: 1. Open web login page. 2. Select role Operator. 3. Enter valid Operator email and password. 4. Click "Đăng nhập". | D18: Login succeeds and user is redirected to Operator home/dashboard page. | E18: Active Operator account exists. | F18: Passed | H18: KhoaPA | I18: Passed | K18: DuongNM | L18: Passed | N18: KhoaPA
A19: TC208 | B19: Role mismatch is blocked at login | C19: 1. Open web login page. 2. Select role Admin. 3. Enter credentials of an Operator account. 4. Click "Đăng nhập". | D19: Login is blocked and message about wrong role is shown; user is not redirected to Admin pages. | E19: Valid Operator account exists. | F19: Passed | H19: KhoaPA | I19: Passed | K19: DuongNM | L19: Passed | N19: KhoaPA
A20: TC209 | B20: Required-field validation is shown when email/password are empty | C20: 1. Open web login page. 2. Select role Admin or Operator. 3. Leave Email and Password empty. 4. Click "Đăng nhập". | D20: Validation message requiring input is shown and login request is not sent. | E20: Login page loads successfully. | F20: Passed | H20: KhoaPA | I20: Passed | K20: DuongNM | L20: Passed | N20: KhoaPA

Sheet Forgot & Reset Password Flow
A2: Feature | B2: Forgot & Reset Password Flow | R2: Passed
A3: Test requirement | R3: Failed
A4: Number of TCs | B4: =COUNTA(A12:A995) -> 5 | R4: Pending
A5: Testing Round | B5: Passed | C5: Failed | D5: Pending | E5: N/A | R5: N/A
A6: Round 1 | B6: =COUNTIF($F10:$F993,B5) -> 5 | C6: =COUNTIF($F10:$F993,C5) -> 0 | D6: =COUNTIF($F10:$F993,D5) -> 0 | E6: =COUNTIF($F10:$F993,E5) -> 0
A7: Round 2 | B7: =COUNTIF($I10:$I993,B5) -> 5 | C7: =COUNTIF($I10:$I993,C5) -> 0 | D7: =COUNTIF($I10:$I993,D5) -> 0 | E7: =COUNTIF($I10:$I993,E5) -> 0
A8: Round 3 | B8: =COUNTIF($L10:$L993,B5) -> 5 | C8: =COUNTIF($L10:$L993,C5) -> 0 | D8: =COUNTIF($L10:$L993,D5) -> 0 | E8: =COUNTIF($L10:$L991,E5) -> 0
A10: Test Case ID | B10: Test Case Description | C10: Test Case Procedure | D10: Expected Results | E10: Pre-conditions | F10: Round 1 | G10: Test date | H10: Tester | I10: Round 2 | J10: Test date | K10: Tester | L10: Round 3 | M10: Test date | N10: Tester | O10: Note
A11: Forgot & Reset Password Flow
A12: TC301 | F12: Passed | H12: KhoaPA | I12: Passed | K12: TrungDN | L12: Passed | N12: DuongNM
A13: TC302 | F13: Passed | H13: KhoaPA | I13: Passed | K13: TrungDN | L13: Passed | N13: DuongNM
A14: TC303 | F14: Passed | H14: KhoaPA | I14: Passed | K14: TrungDN | L14: Passed | N14: DuongNM
A15: TC304 | F15: Passed | H15: KhoaPA | I15: Passed | K15: TrungDN | L15: Passed | N15: DuongNM
A16: TC305 | F16: Passed | H16: KhoaPA | I16: Passed | K16: TrungDN | L16: Passed | N16: DuongNM

Sheet Manage User Profile, Avatar & S
A2: Feature | B2: Manage User Profile, Avatar & Settings | R2: Passed
A3: Test requirement | B3: Allow authenticated users to view and update profile/avatar, access settings, manage privacy options, view wallet balance, and log out securely. | R3: Failed
A4: Number of TCs | B4: =COUNTA(A12:A993) -> 7 | R4: Pending
A5: Testing Round | B5: Passed | C5: Failed | D5: Pending | E5: N/A | R5: N/A
A6: Round 1 | B6: =COUNTIF($F10:$F991,B5) -> 7 | C6: =COUNTIF($F10:$F991,C5) -> 0 | D6: =COUNTIF($F10:$F991,D5) -> 0 | E6: =COUNTIF($F10:$F991,E5) -> 0
A7: Round 2 | B7: =COUNTIF($I10:$I991,B5) -> 7 | C7: =COUNTIF($I10:$I991,C5) -> 0 | D7: =COUNTIF($I10:$I991,D5) -> 0 | E7: =COUNTIF($I10:$I991,E5) -> 0
A8: Round 3 | B8: =COUNTIF($L10:$L991,B5) -> 7 | C8: =COUNTIF($L10:$L991,C5) -> 0 | D8: =COUNTIF($L10:$L991,D5) -> 0 | E8: =COUNTIF($L10:$L991,E5) -> 0
A10: Test Case ID | B10: Test Case Description | C10: Test Case Procedure | D10: Expected Results | E10: Pre-conditions | F10: Round 1 | G10: Test date | H10: Tester | I10: Round 2 | J10: Test date | K10: Tester | L10: Round 3 | M10: Test date | N10: Tester | O10: Note
A11: Manage User Profile, Avatar & Settings
A12: TC401 | B12: User profile is displayed correctly | C12: 1. Sign in as Member. 2. Open profile screen. | D12: Profile shows avatar, full name rating, and reputation data correctly. | E12: User account has profile data. | F12: Passed | H12: KhoaPA | I12: Passed | K12: TrungDN | L12: Passed | N12: DuongNM
A13: TC402 | B13: User can open Edit Profile from profile screen | C13: 1. On profile screen, click "Chỉnh Sửa Hồ Sơ". | D13: User is navigated to Edit Profile screen successfully. | E13: User is signed in. | F13: Passed | H13: KhoaPA | I13: Passed | K13: TrungDN | L13: Passed | N13: DuongNM
A14: TC403 | B14: User avatar upload and save works | C14: 1. Open Edit Profile screen. 2. Tap camera icon to choose a new avatar image. 3. Click "Lưu Thay Đổi". | D14: New avatar is displayed and success message "Lưu thành công" appears. | E14: Device photo permission is granted; avatar upload API is available. | F14: Passed | H14: KhoaPA | I14: Passed | K14: TrungDN | L14: Passed | N14: DuongNM
A15: TC404 | B15: User profile information can be updated | C15: 1. Open Edit Profile screen. 2. Update valid profile data (for example name or phone). 3. Click "Lưu Thay Đổi". | D15: Updated data is saved and reflected when returning to profile screen. | E15: Profile update API is available. | F15: Passed | H15: KhoaPA | I15: Passed | K15: TrungDN | L15: Passed | N15: DuongNM
A16: TC405 | B16: User settings screen displays account options | C16: 1. From profile screen, open settings using "Cài Đặt". 2. Verify account options area. | D16: Account options are displayed correctly, including edit profile and change password entries. | E16: User is signed in. | F16: Passed | H16: KhoaPA | I16: Passed | K16: TrungDN | L16: Passed | N16: DuongNM
A17: TC406 | B17: Wallet balance is shown and refreshable in profile screen | C17: 1. On profile screen. 2. Scroll down to see the wallet balance displayed. | D17: Wallet balance is shown in correct currency format; error state is shown appropriately on network/API failure. | E17: Wallet API is available (or test data is configured). | F17: Passed | H17: KhoaPA | I17: Passed | K17: TrungDN | L17: Passed | N17: DuongNM
A18: TC407 | B18: User can log out from settings | C18: 1. Open settings screen "Cài Đặt". 2. Click "Đăng xuất" and confirm. | D18: Session is cleared and user returns to role-selection/login flow. | E18: User is currently signed in. | F18: Passed | H18: KhoaPA | I18: Passed | K18: TrungDN | L18: Passed | N18: DuongNM

Sheet Identity Document Verification
A2: Feature | B2: Identity Document Verification | R2: Passed
A3: Test requirement | R3: Failed
A4: Number of TCs | B4: =COUNTA(A12:A993) -> 7 | R4: Pending
A5: Testing Round | B5: Passed | C5: Failed | D5: Pending | E5: N/A | R5: N/A
A6: Round 1 | B6: =COUNTIF($F10:$F991,B5) -> 7 | C6: =COUNTIF($F10:$F991,C5) -> 0 | D6: =COUNTIF($F10:$F991,D5) -> 0 | E6: =COUNTIF($F10:$F991,E5) -> 0
A7: Round 2 | B7: =COUNTIF($I10:$I991,B5) -> 7 | C7: =COUNTIF($I10:$I991,C5) -> 0 | D7: =COUNTIF($I10:$I991,D5) -> 0 | E7: =COUNTIF($I10:$I991,E5) -> 0
A8: Round 3 | B8: =COUNTIF($L10:$L991,B5) -> 7 | C8: =COUNTIF($L10:$L991,C5) -> 0 | D8: =COUNTIF($L10:$L991,D5) -> 0 | E8: =COUNTIF($L10:$L991,E5) -> 0
A10: Test Case ID | B10: Test Case Description | C10: Test Case Procedure | D10: Expected Results | E10: Pre-conditions | F10: Round 1 | G10: Test date | H10: Tester | I10: Round 2 | J10: Test date | K10: Tester | L10: Round 3 | M10: Test date | N10: Tester | O10: Note
A11: Identity Document Verification
A12: TC501 | F12: Passed | H12: KhoaPA | I12: Passed | K12: TrungDN | L12: Passed | N12: DuongNM
A13: TC501 | F13: Passed | H13: KhoaPA | I13: Passed | K13: TrungDN | L13: Passed | N13: DuongNM
A14: TC501 | F14: Passed | H14: KhoaPA | I14: Passed | K14: TrungDN | L14: Passed | N14: DuongNM
A15: TC501 | F15: Passed | H15: KhoaPA | I15: Passed | K15: TrungDN | L15: Passed | N15: DuongNM
A16: TC501 | F16: Passed | H16: KhoaPA | I16: Passed | K16: TrungDN | L16: Passed | N16: DuongNM
A17: TC501 | F17: Passed | H17: KhoaPA | I17: Passed | K17: TrungDN | L17: Passed | N17: DuongNM
A18: TC501 | F18: Passed | H18: KhoaPA | I18: Passed | K18: TrungDN | L18: Passed | N18: DuongNM

Sheet Create Snake Catching Request
A2: Feature | B2: Create Snake Catching Request (Images, GPS, Species) | R2: Passed
A3: Test requirement | B3: Create request from "Báo Cáo Phát Hiện Rắn" with required location + address detail; support both flows "Chụp Ảnh" and "Chọn Loài Rắn" | R3: Failed
A4: Number of TCs | B4: =COUNTA(A12:A993) -> 8 | R4: Pending
A5: Testing Round | B5: Passed | C5: Failed | D5: Pending | E5: N/A | R5: N/A
A6: Round 1 | B6: =COUNTIF($F10:$F991,B5) -> 8 | C6: =COUNTIF($F10:$F991,C5) -> 0 | D6: =COUNTIF($F10:$F991,D5) -> 0 | E6: =COUNTIF($F10:$F991,E5) -> 0
A7: Round 2 | B7: =COUNTIF($I10:$I991,B5) -> 8 | C7: =COUNTIF($I10:$I991,C5) -> 0 | D7: =COUNTIF($I10:$I991,D5) -> 0 | E7: =COUNTIF($I10:$I991,E5) -> 0
A8: Round 3 | B8: =COUNTIF($L10:$L991,B5) -> 8 | C8: =COUNTIF($L10:$L991,C5) -> 0 | D8: =COUNTIF($L10:$L991,D5) -> 0 | E8: =COUNTIF($L10:$L991,E5) -> 0
A10: Test Case ID | B10: Test Case Description | C10: Test Case Procedure | D10: Expected Results | E10: Pre-conditions | F10: Round 1 | G10: Test date | H10: Tester | I10: Round 2 | J10: Test date | K10: Tester | L10: Round 3 | M10: Test date | N10: Tester | O10: Note
A11: Create Snake Catching Request (Images, GPS, Species)
A12: TC601 | B12: Create request successfully via photo flow (single) | C12: 1) Open Home as Member 2) Open "Báo Cáo Phát Hiện Rắn" 3) Select "1 loài rắn" and click "Tiếp tục" 4) Keep tab "Chụp Ảnh" 5) Add slot-1 image via "Chụp ảnh" or "Album ảnh" 6) Click "Chọn vị trí" and select address or "Lấy vị trí hiện tại" 7) Fill "GHI CHÚ ĐỊA CHỈ CHI TIẾT *" 8) Click "Gửi Báo Cáo" | D12: Request is created and app navigates to success screen with "Yêu Cầu Đã Được Gửi!" | E12: Member logged in; internet available; create-request API available | F12: Passed | H12: TrungDN | I12: Passed | K12: TrungDN | L12: Passed | N12: DuongNM
A13: TC602 | B13: Create request successfully via manual species flow | C13: 1) Open report flow and select "1 loài rắn" -> "Tiếp tục" 2) Switch to tab "Chọn Loài Rắn" 3) Select one species 4) Set location via "Chọn vị trí" dialog 5) Fill "GHI CHÚ ĐỊA CHỈ CHI TIẾT *" 6) Click "Gửi Báo Cáo" | D13: Request is submitted successfully and success screen is shown | E13: Member logged in; species API available | F13: Passed | H13: TrungDN | I13: Passed | K13: TrungDN | L13: Passed | N13: DuongNM
A14: TC603 | B14: Block continue when quantity not selected | C14: 1) Open "Báo Cáo Phát Hiện Rắn" 2) Do not select "1 loài rắn"/"2-5 loài rắn"/"Ổ rắn" 3) Observe "Tiếp tục" | D14: "Tiếp tục" is disabled; cannot go to detail screen | E14: Member is on quantity selection screen | F14: Passed | H14: TrungDN | I14: Passed | K14: TrungDN | L14: Passed | N14: DuongNM
A15: TC604 | B15: Block submit when location is missing | C15: 1) Prepare valid photo/species data in detail screen 2) Fill "GHI CHÚ ĐỊA CHỈ CHI TIẾT *" 3) Keep location unset 4) Trigger submit path | D15: Submission is blocked and snackbar "Vui lòng chọn vị trí trước khi gửi" is shown | E15: Member is on report detail screen | F15: Passed | H15: TrungDN | I15: Passed | K15: TrungDN | L15: Passed | N15: DuongNM
A16: TC605 | B16: Require address detail before submit | C16: 1) In detail screen, set valid location + valid photo/species data 2) Leave "GHI CHÚ ĐỊA CHỈ CHI TIẾT *" empty 3) Observe "Gửi Báo Cáo" | D16: "Gửi Báo Cáo" remains disabled until address detail is entered | E16: Member is on report detail screen | F16: Passed | H16: TrungDN | I16: Passed | K16: TrungDN | L16: Passed | N16: DuongNM
A17: TC606 | B17: No AI detection -> switch to manual species | C17: 1) In tab "Chụp Ảnh", upload image with no AI detection 2) Click "Gửi Báo Cáo" 3) In dialog "Không nhận diện được rắn", click "Chọn loài rắn thủ công" | D17: Dialog closes and app switches to tab "Chọn Loài Rắn" | E17: At least one photo uploaded; AI returns no detection | F17: Passed | H17: TrungDN | I17: Passed | K17: TrungDN | L17: Passed | N17: DuongNM
A18: TC607 | B18: No AI detection -> still continue submit | C18: 1) In tab "Chụp Ảnh", upload image with no AI detection 2) Click "Gửi Báo Cáo" 3) In dialog "Không nhận diện được rắn", click "Tiếp tục gửi" | D18: System still creates request and navigates to success screen | E18: Required fields valid; AI returns no detection | F18: Passed | H18: TrungDN | I18: Passed | K18: TrungDN | L18: Passed | N18: DuongNM
A19: TC608 | B19: Validate species selection in manual tab | C19: 1) Switch to "Chọn Loài Rắn" 2) Set location + fill "GHI CHÚ ĐỊA CHỈ CHI TIẾT *" 3) Do not pick any species 4) Click "Gửi Báo Cáo" | D19: Validation error is shown ("Vui lòng chọn loài rắn" or "Vui lòng chọn ít nhất 1 loài rắn") and request is not submitted | E19: Member is on manual species tab | F19: Passed | H19: TrungDN | I19: Passed | K19: TrungDN | L19: Passed | N19: DuongNM

Sheet Process Catching Deposit (Round
A2: Feature | B2: Process Catching Deposit (Round 1) | R2: Passed
A3: Test requirement | B3: Member can open the deposit payment sheet from snake catching request detail, pay using either SnakeAidPay wallet or PayOS, and the deposit becomes confirmed for the request | R3: Failed
A4: Number of TCs | B4: =COUNTA(A12:A993) -> 8 | R4: Pending
A5: Testing Round | B5: Passed | C5: Failed | D5: Pending | E5: N/A | R5: N/A
A6: Round 1 | B6: =COUNTIF($F10:$F991,B5) -> 8 | C6: =COUNTIF($F10:$F991,C5) -> 0 | D6: =COUNTIF($F10:$F991,D5) -> 0 | E6: =COUNTIF($F10:$F991,E5) -> 0
A7: Round 2 | B7: =COUNTIF($I10:$I991,B5) -> 8 | C7: =COUNTIF($I10:$I991,C5) -> 0 | D7: =COUNTIF($I10:$I991,D5) -> 0 | E7: =COUNTIF($I10:$I991,E5) -> 0
A8: Round 3 | B8: =COUNTIF($L10:$L991,B5) -> 8 | C8: =COUNTIF($L10:$L991,C5) -> 0 | D8: =COUNTIF($L10:$L991,D5) -> 0 | E8: =COUNTIF($L10:$L991,E5) -> 0
A10: Test Case ID | B10: Test Case Description | C10: Test Case Procedure | D10: Expected Results | E10: Pre-conditions | F10: Round 1 | G10: Test date | H10: Tester | I10: Round 2 | J10: Test date | K10: Tester | L10: Round 3 | M10: Test date | N10: Tester | O10: Note
A11: Process Catching Deposit (Round 1)
A12: TC701 | B12: Open deposit payment sheet from request detail | C12: 1) Open Home as Member 2) Open "Hoạt Động" 3) Select 1 booking that needs travel fee payment 4) Click button "Thanh toán phí di chuyển" | D12: Payment sheet opens with title "Thanh toán đặt cọc", subtitle "Chọn phương thức thanh toán", and amount row "Đợt 1 — Đặt cọc" | E12: A snake catching booking exists in Activity and still requires round-1 deposit payment | F12: Passed | H12: TrungDN | I12: Passed | K12: TrungDN | L12: Passed | N12: DuongNM
A13: TC702 | B13: Pay deposit successfully using SnakeAidPay wallet | C13: 1) Open the payment sheet 2) In the card "Ví SnakeAidPay", verify sufficient balance is available 3) Tap "Thanh toán bằng ví" | D13: Deposit payment succeeds and success dialog appears with title "Thanh Toán Thành Công!" and subtitle "Đặt cọc phí di chuyển đã được xác nhận." | E13: Member has enough wallet balance; deposit payment sheet is open | F13: Passed | H13: TrungDN | I13: Passed | K13: TrungDN | L13: Passed | N13: DuongNM
A14: TC703 | B14: Wallet payment is blocked when balance is not enough | C14: 1) Open "Báo Cáo Phát Hiện Rắn" 2) Do not select "1 loài rắn"/"2-5 loài rắn"/"Ổ rắn" 3) Observe "Tiếp tục" | D14: "Tiếp tục" is disabled; cannot go to detail screen | E14: Member is on quantity selection screen | F14: Passed | H14: TrungDN | I14: Passed | K14: TrungDN | L14: Passed | N14: DuongNM
A15: TC704 | B15: Pay deposit through PayOS checkout successfully | C15: 1) Open the payment sheet 2) In the card "PayOS", tap "Thanh toán qua PayOS" 3) Complete payment on the PayOS checkout page 4) Return to the app via deep link or app resume | D15: PayOS checkout opens, payment is confirmed, and the request is updated to deposit-paid state | E15: PayOS service is available; request has a valid deposit amount | F15: Passed | H15: TrungDN | I15: Passed | K15: TrungDN | L15: Passed | N15: DuongNM
A16: TC705 | B16: PayOS payment updates request state after return | C16: 1) Start a deposit payment through PayOS 2) Finish the payment successfully 3) Wait for the app to verify the deep link return | D16: The app recognizes the returned payment, clears the pending PayOS context, and the booking shows the deposit as confirmed | E16: A PayOS payment link was created for the current request | F16: Passed | H16: TrungDN | I16: Passed | K16: TrungDN | L16: Passed | N16: DuongNM
A17: TC706 | B17: Cancel PayOS checkout and keep deposit unpaid | C17: 1) Open the payment sheet 2) Tap "Thanh toán qua PayOS" 3) Cancel or close the checkout page before payment is confirmed 4) Return to the request detail screen | D17: Deposit remains unpaid and the request stays in the waiting-for-deposit state | E17: PayOS checkout can be opened from the current request | F17: Passed | H17: TrungDN | I17: Passed | K17: TrungDN | L17: Passed | N17: DuongNM
A18: TC707 | B18: Deposit payment is not allowed when no amount is available | C18: 1) Open a request detail screen that has no valid amount for round-1 payment 2) Open the deposit action if visible or trigger the payment action | D18: App shows the snackbar "Không có thông tin giá để thanh toán" and does not open checkout | E18: Request data is missing deposit amount or estimated price | F18: Passed | H18: TrungDN | I18: Passed | K18: TrungDN | L18: Passed | N18: DuongNM
A19: TC708 | B19: Deposit confirmation enables next rescue flow state | C19: 1) Complete a round-1 payment by wallet or PayOS 2) Reopen the request detail screen 3) Verify the payment state area | D19: The request reflects that round-1 deposit is confirmed and the payment entry changes to "Đã Thanh Toán Phí Di Chuyển" | E19: Deposit payment has been confirmed by the backend | F19: Passed | H19: TrungDN | I19: Passed | K19: TrungDN | L19: Passed | N19: DuongNM

Sheet Operator Verification & Assignm
A2: Feature | B2: Operator Verification & Assignment | R2: Passed
A3: Test requirement | B3: Verify operator can process snake-catching requests on dashboard with correct status transitions, dispatch constraints, and UI feedback | R3: Failed
A4: Number of TCs | B4: =COUNTA(A12:A991) -> 6 | R4: Pending
A5: Testing Round | B5: Passed | C5: Failed | D5: Pending | E5: N/A | R5: N/A
A6: Round 1 | B6: =COUNTIF($F10:$F989,B5) -> 6 | C6: =COUNTIF($F10:$F989,C5) -> 0 | D6: =COUNTIF($F10:$F989,D5) -> 0 | E6: =COUNTIF($F10:$F989,E5) -> 0
A7: Round 2 | B7: =COUNTIF($I10:$I989,B5) -> 6 | C7: =COUNTIF($I10:$I989,C5) -> 0 | D7: =COUNTIF($I10:$I989,D5) -> 0 | E7: =COUNTIF($I10:$I989,E5) -> 0
A8: Round 3 | B8: =COUNTIF($L10:$L989,B5) -> 6 | C8: =COUNTIF($L10:$L989,C5) -> 0 | D8: =COUNTIF($L10:$L989,D5) -> 0 | E8: =COUNTIF($L10:$L989,E5) -> 0
A10: Test Case ID | B10: Test Case Description | C10: Test Case Procedure | D10: Expected Results | E10: Pre-conditions | F10: Round 1 | G10: Test date | H10: Tester | I10: Round 2 | J10: Test date | K10: Tester | L10: Round 3 | M10: Test date | N10: Tester | O10: Note
A11: Operator Verification & Assignment
A12: TC801 | B12: Confirm snake-catching request successfully (Pending -> Confirmed) | C12: 1) Login with Operator account 2) Open Operator Dashboard 3) In tab "Bắt rắn", select a request with status "Chờ xác minh" 4) Open request detail modal 5) Click "Xác nhận yêu cầu" | D12: Request is confirmed; status badge in detail becomes "Đã xác nhận"; success toast "Yêu cầu đã được xác nhận." is shown | E12: Operator account exists; at least one active request in Pending state | F12: Passed | H12: TrungDN | I12: Passed | K12: KhoaPA | L12: Passed | N12: TrungDN
A13: TC802 | B13: Assign rescuer successfully (Confirmed -> Assigned) | C13: 1) Open a request already in status "Đã xác nhận" 2) Click "Điều phối rescuer" 3) In dispatch modal, select one available rescuer 4) Click "Xác nhận điều phối" | D13: Dispatch completes; success toast "Điều phối đội cứu hộ thành công." is shown; request detail displays assigned rescuer id in "Rescuer được phân công" | E13: Request is Confirmed; at least one rescuer is online and available | F13: Passed | H13: TrungDN | I13: Passed | K13: KhoaPA | L13: Passed | N13: TrungDN
A14: TC803 | B14: Cannot dispatch when no rescuer is selected | C14: 1) Open request detail in Confirmed state 2) Click "Điều phối rescuer" 3) Do not select any rescuer in list 4) Observe action button | D14: Button "Xác nhận điều phối" remains disabled until a rescuer is selected | E14: Request is Confirmed; dispatch modal can be opened | F14: Passed | H14: TrungDN | I14: Passed | K14: KhoaPA | L14: Passed | N14: DuongNM
A15: TC804 | B15: Show empty-state when no eligible rescuer exists | C15: 1) Open dispatch modal for a Confirmed request 2) Keep filters "Chỉ trong ca" and "Chỉ online" enabled 3) Ensure no rescuer satisfies current filters | D15: Empty-state message "Không có đội cứu hộ phù hợp bộ lọc." is shown; no dispatch success toast appears | E15: Request is Confirmed; test data has no matching rescuer by shift/online filters | F15: Passed | H15: TrungDN | I15: Passed | K15: KhoaPA | L15: Passed | N15: DuongNM
A16: TC805 | B16: Cancel request from Confirmed state | C16: 1) Open detail of a request in Confirmed state 2) Click "Hủy yêu cầu" 3) Wait for dashboard refresh | D16: Success toast "Yêu cầu đã được hủy." is shown; request is removed from active request list | E16: Request is Confirmed and cancellable by operator | F16: Passed | H16: TrungDN | I16: Passed | K16: KhoaPA | L16: Passed | N16: DuongNM
A17: TC806 | B17: Cancel request from Assigned state | C17: 1) Open detail of a request already assigned 2) Click "Hủy yêu cầu" 3) Confirm dashboard list after action | D17: Success toast "Yêu cầu đã được hủy." is shown; active list no longer contains cancelled request | E17: Request is Assigned and appears in active request list | F17: Passed | H17: TrungDN | I17: Passed | K17: KhoaPA | L17: Passed | N17: DuongNM

Sheet Rescuer EnRoute & Arrived Track
A2: Feature | B2: Rescuer EnRoute & Arrived Tracking | R2: Passed
A3: Test requirement | B3: Rescuer receives assigned mission, starts moving (EnRoute), updates arrival (Arrived), and the app reflects tracking state correctly | R3: Failed
A4: Number of TCs | B4: =COUNTA(A12:A991) -> 6 | R4: Pending
A5: Testing Round | B5: Passed | C5: Failed | D5: Pending | E5: N/A | R5: N/A
A6: Round 1 | B6: =COUNTIF($F10:$F989,B5) -> 6 | C6: =COUNTIF($F10:$F989,C5) -> 0 | D6: =COUNTIF($F10:$F989,D5) -> 0 | E6: =COUNTIF($F10:$F989,E5) -> 0
A7: Round 2 | B7: =COUNTIF($I10:$I989,B5) -> 6 | C7: =COUNTIF($I10:$I989,C5) -> 0 | D7: =COUNTIF($I10:$I989,D5) -> 0 | E7: =COUNTIF($I10:$I989,E5) -> 0
A8: Round 3 | B8: =COUNTIF($L10:$L989,B5) -> 6 | C8: =COUNTIF($L10:$L989,C5) -> 0 | D8: =COUNTIF($L10:$L989,D5) -> 0 | E8: =COUNTIF($L10:$L989,E5) -> 0
A10: Test Case ID | B10: Test Case Description | C10: Test Case Procedure | D10: Expected Results | E10: Pre-conditions | F10: Round 1 | G10: Test date | H10: Tester | I10: Round 2 | J10: Test date | K10: Tester | L10: Round 3 | M10: Test date | N10: Tester | O10: Note
A11: Rescuer EnRoute & Arrived Tracking
A12: TC901 | B12: Open assigned mission and verify start-move action | C12: 1) Login as Rescuer 2) Open "Hoạt Động" tab 3) Click "Xem Chi Tiết" 3) Verify payment check section and primary action area | D12: Primary action "BẮT ĐẦU DI CHUYỂN" is visible; when deposit is not confirmed, button remains disabled and payment hint is shown | E12: A mission is assigned to current rescuer; request is in Assigned stage | F12: Passed | H12: TrungDN | I12: Passed | K12: KhoaPA | L12: Passed | N12: TrungDN
A13: TC902 | B13: Start mission transitions to EnRoute screen | C13: 1) Open assigned mission detail with deposit confirmed 2) Tap "BẮT ĐẦU DI CHUYỂN" 3) Wait for navigation | D13: App starts mission and opens EnRoute screen with header text "ĐANG DI CHUYỂN" | E13: Deposit is confirmed and missionId is available | F13: Passed | H13: TrungDN | I13: Passed | K13: KhoaPA | L13: Passed | N13: TrungDN
A14: TC903 | B14: EnRoute screen shows navigation and call tools | C14: 1) From EnRoute screen, inspect top controls 2) Tap navigation icon (external map) 3) Tap call icon when customer phone exists | D14: External navigation can be launched; call action opens phone dialer; EnRoute screen remains stable | E14: Mission is in EnRoute; request has destination and customer phone number | F14: Passed | H14: TrungDN | I14: Passed | K14: KhoaPA | L14: Passed | N14: TrungDN
A15: TC904 | B15: Arrived action is gated by distance > 1 km | C15: 1) Start in EnRoute while still far from destination (> 1 km) 2) Observe distance hint panel and action area | D15: UI shows hint text similar to "Còn cách ... nút "Đã đến nơi" hiện trong vòng 1 km" and arrival action is not available for confirmation | E15: Mission is EnRoute and live location is available with distance > 1 km | F15: Passed | H15: TrungDN | I15: Passed | K15: KhoaPA | L15: Passed | N15: TrungDN
A16: TC905 | B16: Arrived action appears within 1 km | C16: 1) Move/simulate location to within 1 km of destination 2) Observe EnRoute action area | D16: Floating action "ĐÃ ĐẾN NƠI" appears and hint changes to "Bạn đã gần đến nơi! Bấm "ĐÃ ĐẾN NƠI" ở phía trên" | E16: Mission is EnRoute and distance can be updated | F16: Passed | H16: TrungDN | I16: Passed | K16: KhoaPA | L16: Passed | N16: TrungDN
A17: TC906 | B17: Choosing "Đã đến nơi" transitions mission to Arrived flow | C17: 1) Open dialog "Xác nhận đến nơi" 2) Tap "Đã đến nơi" 3) Wait for API update and screen transition 4) Reopen job list/detail to verify status labels | D17: System calls arrived update, navigates to tracking flow, and mission status reflects Arrived (labels such as "Đã đến nơi" in job status) | E17: Mission is EnRoute; arrived endpoint is reachable | F17: Passed | H17: TrungDN | I17: Passed | K17: KhoaPA | L17: Passed | N17: TrungDN

Sheet Rescuer Mission Execution & Evi
A2: Feature | B2: Rescuer Mission Execution & Evidence Upload | R2: Passed
A3: Test requirement | B3: Rescuer executes on-site mission, uploads evidence photos, confirms snake details and environment, then submits final mission result to customer | R3: Failed
A4: Number of TCs | B4: =COUNTA(A12:A991) -> 6 | R4: Pending
A5: Testing Round | B5: Passed | C5: Failed | D5: Pending | E5: N/A | R5: N/A
A6: Round 1 | B6: =COUNTIF($F10:$F989,B5) -> 6 | C6: =COUNTIF($F10:$F989,C5) -> 0 | D6: =COUNTIF($F10:$F989,D5) -> 0 | E6: =COUNTIF($F10:$F989,E5) -> 0
A7: Round 2 | B7: =COUNTIF($I10:$I989,B5) -> 6 | C7: =COUNTIF($I10:$I989,C5) -> 0 | D7: =COUNTIF($I10:$I989,D5) -> 0 | E7: =COUNTIF($I10:$I989,E5) -> 0
A8: Round 3 | B8: =COUNTIF($L10:$L989,B5) -> 6 | C8: =COUNTIF($L10:$L989,C5) -> 0 | D8: =COUNTIF($L10:$L989,D5) -> 0 | E8: =COUNTIF($L10:$L989,E5) -> 0
A10: Test Case ID | B10: Test Case Description | C10: Test Case Procedure | D10: Expected Results | E10: Pre-conditions | F10: Round 1 | G10: Test date | H10: Tester | I10: Round 2 | J10: Test date | K10: Tester | L10: Round 3 | M10: Test date | N10: Tester | O10: Note
A11: Rescuer EnRoute & Arrived Tracking
A12: TC1001 | B12: Open mission execution screen after Arrived | C12: 1) Login as Rescuer 2) Open "Hoạt Động" Tab 3) Open an assigned mission already at Arrived state 4) Enter mission execution screen | D12: Screen title shows "Đang Bắt Rắn" with processing badge "ĐANG XỬ LÝ" | E12: Mission status is Arrived and belongs to current rescuer | F12: Passed | H12: TrungDN | I12: Passed | K12: KhoaPA | L12: Passed | N12: TrungDN
A13: TC1002 | B13: Start mission transitions to EnRoute screen | C13: 1) Login as Rescuer 2) Open "Hoạt Động" Tab 3) Enter mission execution screen 4)On "Đang Bắt Rắn" screen, tap area "Chụp ảnh rắn sau khi bắt" 5) Capture one photo from camera 6) Wait for upload | D13: Photo thumbnail appears, upload state completes, and progress label updates to "Đã tải 1/1" (or equivalent done count) | E13: Camera permission granted and network available | F13: Passed | H13: TrungDN | I13: Passed | K13: KhoaPA | L13: Passed | N13: TrungDN
A14: TC1003 | B14: Upload failure shows retry behavior | C14: 1) Login as Rescuer 2) Open "Hoạt Động" Tab 3) Enter mission execution screen 4)On "Đang Bắt Rắn" screen, tap area "Chụp ảnh rắn sau khi bắt" 5) Capture one photo from camera 6) Wait for upload 7) Trigger a photo upload failure (unstable network / server error) 8) Tap "Thử lại" on failed photo | D14: Snackbar appears with "Tải ảnh thất bại. Nhấn ’Thử lại’ trên ảnh để upload lại.", then retry can set state back to uploaded | E14: At least one captured photo exists and upload fails | F14: Passed | H14: TrungDN | I14: Passed | K14: KhoaPA | L14: Passed | N14: TrungDN
A15: TC1004 | B15: Complete button remains locked without uploaded photo | C15: 1) Login as Rescuer 2) Open "Hoạt Động" Tab 3) Enter mission execution screen 4)On "Đang Bắt Rắn" screen | D15: Bottom button is disabled and text shows "CẦN ÍT NHẤT 1 ẢNH" | E15: Rescuer has not uploaded any successful evidence photo | F15: Passed | H15: TrungDN | I15: Passed | K15: KhoaPA | L15: Passed | N15: TrungDN
A16: TC1005 | B16: Navigate to result confirmation after having uploaded photo | C16: "1) Login as Rescuer 2) Open "Hoạt Động" Tab 3) Enter mission execution screen 4)On "Đang Bắt Rắn" screen, tap area "Chụp ảnh rắn sau khi bắt" 5) Capture one photo from camera 6) Wait for upload 7) Upload at least one evidence photo successfully 8) Tap bottom button "HOÀN THÀNH BẮT RẮN" | D16: App navigates to screen "Xác Nhận Hoàn Thành" | E16: Mission is EnRoute and distance can be updated | F16: Passed | H16: TrungDN | I16: Passed | K16: KhoaPA | L16: Passed | N16: TrungDN
A17: TC1006 | B17: Choosing "Đã đến nơi" transitions mission to Arrived flow | C17: 1) Open dialog "Xác nhận đến nơi" 2) Tap "Đã đến nơi" 3) Wait for API update and screen transition 4) Reopen job list/detail to verify status labels | D17: System calls arrived update, navigates to tracking flow, and mission status reflects Arrived (labels such as "Đã đến nơi" in job status) | E17: Mission is EnRoute; arrived endpoint is reachable | F17: Passed | H17: TrungDN | I17: Passed | K17: KhoaPA | L17: Passed | N17: TrungDN

Sheet View & Filter Expert Directory
A2: Feature | B2: View & Filter Expert Directory | R2: Passed
A3: Test requirement | B3: Load expert directory from API, apply specialty/sort/search filters, keep realtime online presence in sync via SignalR, and open expert detail with complete profile data. | R3: Failed
A4: Number of TCs | B4: =COUNTA(A12:A991) -> 5 | R4: Pending
A5: Testing Round | B5: Passed | C5: Failed | D5: Pending | E5: N/A | R5: N/A
A6: Round 1 | B6: =COUNTIF($F10:$F989,B5) -> 5 | C6: =COUNTIF($F10:$F989,C5) -> 0 | D6: =COUNTIF($F10:$F989,D5) -> 0 | E6: =COUNTIF($F10:$F989,E5) -> 0
A7: Round 2 | B7: =COUNTIF($I10:$I989,B5) -> 5 | C7: =COUNTIF($I10:$I989,C5) -> 0 | D7: =COUNTIF($I10:$I989,D5) -> 0 | E7: =COUNTIF($I10:$I989,E5) -> 0
A8: Round 3 | B8: =COUNTIF($L10:$L989,B5) -> 5 | C8: =COUNTIF($L10:$L989,C5) -> 0 | D8: =COUNTIF($L10:$L989,D5) -> 0 | E8: =COUNTIF($L10:$L989,E5) -> 0
A10: Test Case ID | B10: Test Case Description | C10: Test Case Procedure | D10: Expected Results | E10: Pre-conditions | F10: Round 1 | G10: Test date | H10: Tester | I10: Round 2 | J10: Test date | K10: Tester | L10: Round 3 | M10: Test date | N10: Tester | O10: Note
A11: View & Filter Expert Directory
A12: TC1801 | B12: Expert list loads successfully with API data | C12: 1. Sign in as Member. 2. Click "Tư vấn chuyên gia" on Member home screen. 3. Click "đặt lịch mới" to find "Chuyên Gia Rắn". 4. Wait for list loading to complete. | D12: The app calls expert directory API and displays expert cards with name, specialty, rating, fee, and online indicator; online status is updated by SignalR snapshot/delta events when available. | E12: Member account is authenticated; expert API and SignalR hub are reachable. | F12: Passed | H12: KhoaPA | I12: Passed | K12: TrungDN | L12: Passed | N12: KhoaPA
A13: TC1802 | B13: Specialty filter and sort option are applied correctly | C13: 1. On "Chuyên Gia Rắn" screen. 2. Open "Sắp xếp theo" and choose "Đánh giá cao nhất". | D13: The displayed list is filtered by selected specialty and ordered by selected sort rule; active filter chips are shown and removable. | E13: Expert list has at least 3 records with different ratings. | F13: Passed | H13: KhoaPA | I13: Passed | K13: TrungDN | L13: Passed | N13: KhoaPA
A14: TC1803 | B14: Keyword search returns matching experts | C14: 1. On "Chuyên Gia Rắn", click search icon. 2. Enter a keyword from expert name. | D14: The list shows only matching experts and updates stats text with result count for the entered query. | E14: Expert list data includes records matching the keyword. | F14: Passed | H14: KhoaPA | I14: Passed | K14: TrungDN | L14: Passed | N14: KhoaPA
A15: TC1804 | B15: Expert detail loads profile, reviews, and availability in one flow | C15: 1. From expert list, open one expert card. 2. Observe profile sections "Giới Thiệu", "Kinh Nghiệm", "Thống Kê", "Phí Tư Vấn", "Lịch Trống", and review area. | D15: Expert detail screen is populated with API data from profile/reviews/time-slots aggregation. | E15: Expert detail endpoints are available for the selected expert. | F15: Passed | H15: KhoaPA | I15: Passed | K15: TrungDN | L15: Passed | N15: KhoaPA
A16: TC1805 | B16: Continue from expert detail to service selection | C16: 1. On expert detail screen, click "Đặt Tư Vấn". | D16: The app navigates to service selection route for the same expert and shows both consultation options. | E16: Expert detail screen is loaded successfully. | F16: Passed | H16: KhoaPA | I16: Passed | K16: TrungDN | L16: Passed | N16: KhoaPA

Sheet Book Instant Consultation
A2: Feature | B2: Book Instant Consultation | R2: Passed
A3: Test requirement | B3: Allow instant consultation booking only when expert is online, collect problem description, create emergency request, process payment, and track acceptance status in realtime. | R3: Failed
A4: Number of TCs | B4: =COUNTA(A12:A991) -> 5 | R4: Pending
A5: Testing Round | B5: Passed | C5: Failed | D5: Pending | E5: N/A | R5: N/A
A6: Round 1 | B6: =COUNTIF($F10:$F989,B5) -> 5 | C6: =COUNTIF($F10:$F989,C5) -> 0 | D6: =COUNTIF($F10:$F989,D5) -> 0 | E6: =COUNTIF($F10:$F989,E5) -> 0
A7: Round 2 | B7: =COUNTIF($I10:$I989,B5) -> 5 | C7: =COUNTIF($I10:$I989,C5) -> 0 | D7: =COUNTIF($I10:$I989,D5) -> 0 | E7: =COUNTIF($I10:$I989,E5) -> 0
A8: Round 3 | B8: =COUNTIF($L10:$L989,B5) -> 5 | C8: =COUNTIF($L10:$L989,C5) -> 0 | D8: =COUNTIF($L10:$L989,D5) -> 0 | E8: =COUNTIF($L10:$L989,E5) -> 0
A10: Test Case ID | B10: Test Case Description | C10: Test Case Procedure | D10: Expected Results | E10: Pre-conditions | F10: Round 1 | G10: Test date | H10: Tester | I10: Round 2 | J10: Test date | K10: Tester | L10: Round 3 | M10: Test date | N10: Tester | O10: Note
A11: Book Instant Consultation
A12: TC1901 | B12: Instant consultation option is disabled when expert is offline | C12: 1. Open service selection for an expert currently shown as offline. 2. Observe instant card "Tư Vấn Ngay" and the button "Chọn Tư Vấn Ngay". | D12: Instant action is disabled; user cannot proceed until expert is online. | E12: Selected expert is offline according to realtime presence. | F12: Passed | H12: KhoaPA | I12: Passed | K12: TrungDN | L12: Passed | N12: KhoaPA
A13: TC1902 | B13: Instant flow moves to documents and requires problem description | C13: 1. Open service selection for an online expert and click "Chọn Tư Vấn Ngay". 2. On "Tài Liệu Tư Vấn", leave "Mô Tả Vấn Đề" empty and click continue button. | D13: App stays on documents screen and shows validation message "Vui lòng mô tả vấn đề của bạn". | E13: Selected expert is online. | F13: Passed | H13: KhoaPA | I13: Passed | K13: TrungDN | L13: Passed | N13: KhoaPA
A14: TC1903 | B14: Instant payment with SnakeAidPay creates request and opens waiting modal | C14: 1. Fill valid problem description on instant documents screen. 2. Continue to "Xác Nhận & Thanh Toán". 3. Select "SnakeAid Pay", accept "Chính Sách Thanh Toán", and click "Xác Nhận & Thanh Toán". | D14: App creates emergency request and shows emergency waiting modal with message "Đã thanh toán. Đang chờ chuyên gia phản hồi...". | E14: Member wallet balance is sufficient; instant payment API is available. | F14: Passed | H14: KhoaPA | I14: Passed | K14: TrungDN | L14: Passed | N14: KhoaPA
A15: TC1904 | B15: Instant payment with PayOS launches external checkout and supports callback confirmation | C15: 1. From instant payment screen, select "PayOS" and confirm payment. 2. Complete payment in PayOS and return to app via callback/deep link. | D15: App opens PayOS checkout URL, verifies callback, and enters emergency waiting modal; fallback confirmation API is used if needed before finalizing. | E15: PayOS integration and deep-link callback are configured. | F15: Passed | H15: KhoaPA | I15: Passed | K15: TrungDN | L15: Passed | N15: DuongNM
A16: TC1905 | B16: Instant waiting handles realtime acceptance and routes to video waiting room | C16: 1. After instant payment, keep emergency waiting modal open. 2. From expert side, accept the same request. | D16: Member waiting modal status changes to accepted and app navigates to member video waiting room route with the accepted consultationId. | E16: Expert account can receive and accept the same emergency request. | F16: Passed | H16: KhoaPA | I16: Passed | K16: TrungDN | L16: Passed | N16: KhoaPA

Sheet Book Scheduled Consultation
A2: Feature | B2: Book Scheduled Consultation | R2: Passed
A3: Test requirement | B3: Show available time slots from API, enforce valid slot/problem input, create booking with real timeSlotId, and continue to payment with booking identifiers. | R3: Failed
A4: Number of TCs | B4: =COUNTA(A12:A991) -> 5 | R4: Pending
A5: Testing Round | B5: Passed | C5: Failed | D5: Pending | E5: N/A | R5: N/A
A6: Round 1 | B6: =COUNTIF($F10:$F989,B5) -> 5 | C6: =COUNTIF($F10:$F989,C5) -> 0 | D6: =COUNTIF($F10:$F989,D5) -> 0 | E6: =COUNTIF($F10:$F989,E5) -> 0
A7: Round 2 | B7: =COUNTIF($I10:$I989,B5) -> 5 | C7: =COUNTIF($I10:$I989,C5) -> 0 | D7: =COUNTIF($I10:$I989,D5) -> 0 | E7: =COUNTIF($I10:$I989,E5) -> 0
A8: Round 3 | B8: =COUNTIF($L10:$L989,B5) -> 5 | C8: =COUNTIF($L10:$L989,C5) -> 0 | D8: =COUNTIF($L10:$L989,D5) -> 0 | E8: =COUNTIF($L10:$L989,E5) -> 0
A10: Test Case ID | B10: Test Case Description | C10: Test Case Procedure | D10: Expected Results | E10: Pre-conditions | F10: Round 1 | G10: Test date | H10: Tester | I10: Round 2 | J10: Test date | K10: Tester | L10: Round 3 | M10: Test date | N10: Tester | O10: Note
A11: Book Scheduled Consultation
A12: TC2001 | B12: Scheduled option is unavailable when expert has no availability slot | C12: 1. Open service selection for an expert with no available slots. 2. Observe "Đặt Lịch Tư Vấn" card and click "Chọn Đặt Lịch". | D12: App shows "Chuyên gia chưa có lịch trống" and disables booking action; user cannot proceed to time selection. | E12: Selected expert has empty availability slot from API. | F12: Passed | H12: KhoaPA | I12: Passed | K12: TrungDN | L12: Passed | N12: KhoaPA
A13: TC2002 | B13: Time selection shows only valid future slots and requires selection | C13: 1. Open "Chọn Thời Gian" for an expert with availability. 2. Select no date/time. | D13: App blocks progression and shows "Vui lòng chọn ngày và giờ tư vấn"; date/slot grid only contains non-expired slots according to current time rules. | E13: Expert time-slot API returns at least one available day. | F13: Passed | H13: KhoaPA | I13: Passed | K13: TrungDN | L13: Passed | N13: KhoaPA
A14: TC2003 | B14: Scheduled documents call create-booking API with real timeSlotId | C14: 1. Select date and slot, then navigate to "Tài Liệu Tư Vấn". 2. Enter valid "Mô Tả Vấn Đề" and click "Xác Nhận Đặt Lịch". | D14: App calls scheduled booking API and receives booking with bookingId/consultationId; then navigates to payment confirmation with those identifiers in flow data. | E14: Selected slot is still available; booking API is reachable. | F14: Passed | H14: KhoaPA | I14: Passed | K14: TrungDN | L14: Passed | N14: KhoaPA
A15: TC2004 | B15: Concurrent slot conflict returns friendly message | C15: 1. Reach scheduled documents screen with a slot that has just been taken by another user. 2. Click "Xác Nhận Đặt Lịch". | D15: App stays on screen and shows conflict message "Khung giờ này vừa được đặt bởi người khác. Vui lòng chọn giờ khác.". | E15: Slot conflict can be simulated (backend returns HTTP 409). | F15: Passed | H15: KhoaPA | I15: Passed | K15: TrungDN | L15: Passed | N15: KhoaPA
A16: TC2005 | B16: Scheduled payment success sends user back to consultation home with highlight | C16: 1. Complete scheduled payment (Wallet or PayOS callback success). 2. Observe navigation result. | D16: App invalidates bookings data and routes to consultation home, passing new consultation/booking ID so the corresponding card is highlighted. | E16: Scheduled booking exists in pending-payment state. | F16: Passed | H16: KhoaPA | I16: Passed | K16: TrungDN | L16: Passed | N16: DuongNM

Sheet Process Consultation Escrow Pay
A2: Feature | B2: Process Consultation Escrow Payment | R2: Passed
A3: Test requirement | B3: Enforce payment policy acknowledgment, support PayOS and wallet flows, handle insufficient wallet/top-up and callback verification, and keep consultation payment status consistent. | R3: Failed
A4: Number of TCs | B4: =COUNTA(A12:A992) -> 6 | R4: Pending
A5: Testing Round | B5: Passed | C5: Failed | D5: Pending | E5: N/A | R5: N/A
A6: Round 1 | B6: =COUNTIF($F10:$F990,B5) -> 6 | C6: =COUNTIF($F10:$F990,C5) -> 0 | D6: =COUNTIF($F10:$F990,D5) -> 0 | E6: =COUNTIF($F10:$F990,E5) -> 0
A7: Round 2 | B7: =COUNTIF($I10:$I990,B5) -> 6 | C7: =COUNTIF($I10:$I990,C5) -> 0 | D7: =COUNTIF($I10:$I990,D5) -> 0 | E7: =COUNTIF($I10:$I990,E5) -> 0
A8: Round 3 | B8: =COUNTIF($L10:$L990,B5) -> 6 | C8: =COUNTIF($L10:$L990,C5) -> 0 | D8: =COUNTIF($L10:$L990,D5) -> 0 | E8: =COUNTIF($L10:$L990,E5) -> 0
A10: Test Case ID | B10: Test Case Description | C10: Test Case Procedure | D10: Expected Results | E10: Pre-conditions | F10: Round 1 | G10: Test date | H10: Tester | I10: Round 2 | J10: Test date | K10: Tester | L10: Round 3 | M10: Test date | N10: Tester | O10: Note
A11: Process Consultation Escrow Payment
A12: TC2101 | B12: Payment cannot proceed before policy acknowledgment | C12: 1. Open "Xác Nhận & Thanh Toán". 2. Do not tick "Tôi đã đọc và hiểu Chính Sách Thanh Toán bên trên.". 3. Click "Xác Nhận & Thanh Toán". | D12: App does not submit payment and shows warning requiring policy acknowledgment. | E12: Payment confirmation screen is loaded with valid booking or instant flow. | F12: Passed | H12: KhoaPA | I12: Passed | K12: TrungDN | L12: Passed | N12: KhoaPA
A13: TC2102 | B13: Security and policy content reflect escrow behavior | C13: 1. Open payment screen and expand "Chính Sách Thanh Toán". 2. Review security box and policy bullets. | D13: UI explains escrow handling and non-self-cancel rule after successful payment; instant flow policy includes refund rule when expert does not accept. | E13: Payment confirmation screen is reachable. | F13: Passed | H13: KhoaPA | I13: Passed | K13: TrungDN | L13: Passed | N13: KhoaPA
A14: TC2103 | B14: Wallet method fails gracefully on insufficient balance and supports top-up | C14: 1. Select "SnakeAid Pay" with wallet balance lower than consultation price. 2. Open wallet confirmation dialog and click "Nạp ví ngay". | D14: Confirm action remains disabled until balance is enough; app opens PayOS top-up, then refreshes wallet and allows payment after successful top-up callback/verification. | E14: Wallet exists with insufficient balance; top-up API and callback are available. | F14: Passed | H14: KhoaPA | I14: Passed | K14: TrungDN | L14: Passed | N14: KhoaPA
A15: TC2104 | B15: PayOS flow handles callback success and fallback confirm | C15: 1. Select "PayOS" and confirm consultation payment. 2. Complete checkout and return to app. | D15: App verifies callback event; if pending, fallback confirm API is triggered; on confirmed status, app routes to waiting/home flow and clears pending PayOS context. | E15: PayOS checkout can be completed; deep-link callback is configured. | F15: Passed | H15: KhoaPA | I15: Passed | K15: DuongNM | L15: Passed | N15: DuongNM
A16: TC2105 | B16: PayOS cancellation callback is handled without corrupting state | C16: 1. Start PayOS consultation payment. 2. Cancel payment from PayOS and return to app. | D16: App shows cancellation message "Bạn đã hủy thanh toán PayOS.", stops loading state, and keeps consultation unpaid. | E16: PayOS cancellation callback is deliverable. | F16: Passed | H16: KhoaPA | I16: Passed | K16: DuongNM | L16: Passed | N16: DuongNM
A17: TC2106 | B17: Backend payment-method lock forces PayOS when request was initiated with PayOS | C17: 1. Start a payment on a booking/request via PayOS. 2. Return and attempt to pay same reference via "SnakeAid Pay". | D17: App detects backend conflict and locks method to PayOS, showing guidance message to continue with PayOS only. | E17: Backend returns already-paid/locked payment response for the same reference. | F17: Passed | H17: KhoaPA | I17: Passed | K17: DuongNM | L17: Passed | N17: DuongNM

Sheet WebRTC Video Room & Waiting Roo
A2: Feature | B2: WebRTC Video Room & Waiting Room Logic | R2: Passed
A3: Test requirement | B3: Enter waiting rooms and video rooms using consultation token APIs, maintain mic/camera state across routes, support in-call chat/media utilities, and complete consultation with review flow. | R3: Failed
A4: Number of TCs | B4: =COUNTA(A12:A991) -> 5 | R4: Pending
A5: Testing Round | B5: Passed | C5: Failed | D5: Pending | E5: N/A | R5: N/A
A6: Round 1 | B6: =COUNTIF($F10:$F989,B5) -> 5 | C6: =COUNTIF($F10:$F989,C5) -> 0 | D6: =COUNTIF($F10:$F989,D5) -> 0 | E6: =COUNTIF($F10:$F989,E5) -> 0
A7: Round 2 | B7: =COUNTIF($I10:$I989,B5) -> 5 | C7: =COUNTIF($I10:$I989,C5) -> 0 | D7: =COUNTIF($I10:$I989,D5) -> 0 | E7: =COUNTIF($I10:$I989,E5) -> 0
A8: Round 3 | B8: =COUNTIF($L10:$L989,B5) -> 5 | C8: =COUNTIF($L10:$L989,C5) -> 0 | D8: =COUNTIF($L10:$L989,D5) -> 0 | E8: =COUNTIF($L10:$L989,E5) -> 0
A10: Test Case ID | B10: Test Case Description | C10: Test Case Procedure | D10: Expected Results | E10: Pre-conditions | F10: Round 1 | G10: Test date | H10: Tester | I10: Round 2 | J10: Test date | K10: Tester | L10: Round 3 | M10: Test date | N10: Tester | O10: Note
A11: WebRTC Video Room & Waiting Room Logic
A12: TC2201 | B12: Member waiting room retrieves LiveKit token and enters video room | C12: 1. From member consultation card, open waiting room and click "Vào phòng". | D12: App requests video token for consultation, then navigates to video consultation screen. | E12: Member is a participant of the consultation; video-token API is available. | F12: Passed | H12: KhoaPA | I12: Passed | K12: TrungDN | L12: Passed | N12: KhoaPA
A13: TC2202 | B13: In-call chat supports text, image upload, typing indicator, and snake lookup helpers | C13: 1. In video consultation, send a text message. 2. Send an image message. 3. Trigger typing indicator and snake search/detail helper. | D13: Text/image messages are sent through chat channel, typing indicator appears/disappears as expected, and snake lookup API returns data in-call. | E13: Chat SignalR and media upload/snake APIs are available. | F13: Passed | H13: KhoaPA | I13: Passed | K13: TrungDN | L13: Passed | N13: KhoaPA
A14: TC2203 | B14: Member can end consultation from waiting room after call and open completion screen | C14: 1. Return from call to waiting room with completion button visible. 2. Click "Hoàn Thành Tư Vấn", then confirm "Kết Thúc" in dialog. | D14: App calls end-consultation API and navigates to "Hoàn Thành Tư Vấn" screen; failure shows non-blocking error snackbar. | E14: Consultation session exists and member has permission to end it. | F14: Passed | H14: KhoaPA | I14: Passed | K14: TrungDN | L14: Passed | N14: KhoaPA
A15: TC2204 | B15: Member completion screen submits review successfully | C15: 1. On completion screen, select star rating and optional feedback tags/text. 2. Click submit action. | D15: App posts consultation review and shows success feedback before navigating back to member home/consultation area. | E15: Completed consultationId is valid for review submission. | F15: Passed | H15: KhoaPA | I15: Passed | K15: TrungDN | L15: Passed | N15: KhoaPA
A16: TC2205 | B16: Expert flow: instant popup accept/reject and waiting-room entry | C16: 1. Sign in as Expert and receive instant request popup "Cần Tư Vấn Ngay". 2. Test "Bắt Đầu Ngay" and "Từ chối" actions in separate runs. | D16: Accept calls emergency accept API and navigates to expert waiting room with consultationId; reject calls reject API and closes popup without navigation. | E16: Expert account is online and receives realtime emergency request events. | F16: Passed | H16: KhoaPA | I16: Passed | K16: TrungDN | L16: Passed | N16: KhoaPA

Sheet Cancellation & Escrow Refund Ha
A2: Feature | B2: Cancellation & Escrow Refund Handling | R2: Passed
A3: Test requirement | B3: Verify implemented cancellation/refund outcomes in member and expert flows, including declined/expired instant requests, cancelled-history display with refund labels, and current expert-side cancellation boundaries. | R3: Failed
A4: Number of TCs | B4: =COUNTA(A12:A990) -> 4 | R4: Pending
A5: Testing Round | B5: Passed | C5: Failed | D5: Pending | E5: N/A | R5: N/A
A6: Round 1 | B6: =COUNTIF($F10:$F988,B5) -> 4 | C6: =COUNTIF($F10:$F988,C5) -> 0 | D6: =COUNTIF($F10:$F988,D5) -> 0 | E6: =COUNTIF($F10:$F988,E5) -> 0
A7: Round 2 | B7: =COUNTIF($I10:$I988,B5) -> 4 | C7: =COUNTIF($I10:$I988,C5) -> 0 | D7: =COUNTIF($I10:$I988,D5) -> 0 | E7: =COUNTIF($I10:$I988,E5) -> 0
A8: Round 3 | B8: =COUNTIF($L10:$L988,B5) -> 4 | C8: =COUNTIF($L10:$L988,C5) -> 0 | D8: =COUNTIF($L10:$L988,D5) -> 0 | E8: =COUNTIF($L10:$L988,E5) -> 0
A10: Test Case ID | B10: Test Case Description | C10: Test Case Procedure | D10: Expected Results | E10: Pre-conditions | F10: Round 1 | G10: Test date | H10: Tester | I10: Round 2 | J10: Test date | K10: Tester | L10: Round 3 | M10: Test date | N10: Tester | O10: Note
A11: Cancellation & Escrow Refund Handling
A12: TC2301 | B12: Member sees refund status when instant request is declined by expert | C12: 1. Member starts paid instant request and waits in emergency waiting modal. 2. Expert declines the request. | D12: Member waiting status becomes declined with refund notice; user can return to consultation home and rebook with another expert. | E12: Instant request is created and paid; expert can decline in time window. | F12: Passed | H12: KhoaPA | I12: Passed | K12: TrungDN | L12: Passed | N12: KhoaPA
A13: TC2302 | B13: Member sees refund status when instant request expires | C13: 1. Member starts paid instant request. 2. Do not accept on expert side until request timeout. | D13: Waiting status changes to expired and informs that money is refunded to wallet; user is prompted to create a new request. | E13: Expiration policy is active on backend. | F13: Passed | H13: KhoaPA | I13: Passed | K13: TrungDN | L13: Passed | N13: KhoaPA
A14: TC2303 | B14: Cancelled consultation history card shows refund and rebook CTA | C14: 1. Open member consultation history tab with at least one cancelled item. 2. Inspect fee row and action buttons. | D14: Cancelled card displays "Đã hoàn tiền" and shows "Đặt Lại" button navigating to expert list; non-cancelled completed cards show review actions instead. | E14: Member account has cancelled and completed consultation records. | F14: Passed | H14: KhoaPA | I14: Passed | K14: TrungDN | L14: Passed | N14: KhoaPA
A15: TC2304 | B15: Payment policy prevents self-cancel expectations after successful payment | C15: 1. On payment screen, review and accept policy. 2. Complete payment successfully. 3. Return to consultation detail/home and look for self-cancel action. | D15: UI behavior is consistent with policy text: no member self-cancel action is provided after successful payment in current mobile flow. | E15: Consultation payment has succeeded. | F15: Passed | H15: KhoaPA | I15: Passed | K15: TrungDN | L15: Passed | N15: KhoaPA

Sheet Operator Dashboard & Admin Dash
A2: Feature | B2: Operator Dashboard & Admin Dashboard | R2: Passed
A3: Test requirement | B3: Verify Admin dashboard analytics, filters, chart rendering, export flow, and Operator dashboard realtime queues/map/action modals with role-gated access. | R3: Failed
A4: Number of TCs | B4: =COUNTA(A12:A999) -> 13 | R4: Pending
A5: Testing Round | B5: Passed | C5: Failed | D5: Pending | E5: N/A | R5: N/A
A6: Round 1 | B6: =COUNTIF($F10:$F997,B5) -> 13 | C6: =COUNTIF($F10:$F997,C5) -> 0 | D6: =COUNTIF($F10:$F997,D5) -> 0 | E6: =COUNTIF($F10:$F997,E5) -> 0
A7: Round 2 | B7: =COUNTIF($I10:$I997,B5) -> 13 | C7: =COUNTIF($I10:$I997,C5) -> 0 | D7: =COUNTIF($I10:$I997,D5) -> 0 | E7: =COUNTIF($I10:$I997,E5) -> 0
A8: Round 3 | B8: =COUNTIF($L10:$L997,B5) -> 13 | C8: =COUNTIF($L10:$L997,C5) -> 0 | D8: =COUNTIF($L10:$L997,D5) -> 0 | E8: =COUNTIF($L10:$L997,E5) -> 0
A10: Test Case ID | B10: Test Case Description | C10: Test Case Procedure | D10: Expected Results | E10: Pre-conditions | F10: Round 1 | G10: Test date | H10: Tester | I10: Round 2 | J10: Test date | K10: Tester | L10: Round 3 | M10: Test date | N10: Tester | O10: Note
A11: Operator Dashboard & Admin Dashboard
A12: TC3401 | B12: Admin dashboard loads KPI cards and charts | C12: 1. Sign in as Admin. 2. Open "Bảng điều khiển" page. 3. Wait for all widgets to load. | D12: KPI cards, revenue/case/profit/commission charts, users timeline, and recent incidents/requests panels are displayed without crash. | E12: Admin account is active; analytics APIs are available. | F12: Passed | H12: KhoaPA | I12: Passed | K12: TrungDN | L12: Passed | N12: TrungDN
A13: TC3402 | B13: Admin period switch updates analytics | C13: 1. On Admin dashboard, switch period Day/Month/Year. 2. Observe chart and KPI values after each switch. | D13: Data is reloaded by selected period and all chart groups stay synchronized to the same period. | E13: Dashboard loaded successfully with non-empty analytics data. | F13: Passed | H13: KhoaPA | I13: Passed | K13: TrungDN | L13: Passed | N13: TrungDN
A14: TC3403 | B14: Admin custom date range is applied | C14: 1. Set From date and To date on dashboard header. 2. Verify values on KPI/charts and recent data sections. | D14: Dashboard reflects selected date range; invalid range is blocked by date picker constraints. | E14: Admin is on dashboard page. | F14: Passed | H14: KhoaPA | I14: Passed | K14: TrungDN | L14: Passed | N14: TrungDN
A15: TC3404 | B15: Admin export Excel works | C15: 1. Click "Xuất Excel" on "Bảng điều khiển" page. 2. Open downloaded file. | D15: Excel file is downloaded and contains expected analytics sheets (revenue/profit/commission/users/cases). | E15: Browser download is enabled; at least one analytics source returns data. | F15: Passed | H15: KhoaPA | I15: Passed | K15: TrungDN | L15: Passed | N15: TrungDN
A16: TC3405 | B16: Admin handles partial analytics source failure | C16: 1. Simulate one or more analytics API failures. 2. Refresh dashboard. | D16: Remaining successful widgets still render; warning/error toast appears appropriately; page does not break. | E16: Test environment can simulate partial API failures. | F16: Passed | H16: KhoaPA | I16: Passed | K16: TrungDN | L16: Passed | N16: TrungDN
A17: TC3406 | B17: Operator dashboard loads map, queues, and rescuer panels | C17: 1. Sign in as Operator. 2. Open Operator dashboard. | D17: Map, incident/request queue panels, rescuer online panel, and summary cards appear. | E17: Operator account is active; incident/request endpoints available. | F17: Passed | H17: KhoaPA | I17: Passed | K17: TrungDN | L17: Passed | N17: TrungDN
A18: TC3407 | B18: Operator handles pending incident alert | C18: 1. Trigger a new incident event. 2. In pending incident alert, test "Xem chi tiết", "Ẩn", and "Xác nhận case" actions. | D18: Alert shows incident id/location; actions work correctly and update queue state. | E18: SignalR/event feed is available; operator has at least one pending incident event. | F18: Passed | H18: DuongNM | I18: Passed | K18: TrungDN | L18: Passed | N18: DuongNM
A19: TC3408 | B19: Operator handles pending snake-catching request alert | C19: 1. Trigger a new snake-catching request event. 2. In pending request alert, test "Xem chi tiết", "Ẩn", and "Xác nhận yêu cầu" actions. | D19: Alert shows request id/location; confirm action updates request state and queue. | E19: SignalR/event feed is available; operator has at least one pending request event. | F19: Passed | H19: DuongNM | I19: Passed | K19: TrungDN | L19: Passed | N19: DuongNM
A20: TC3409 | B20: Operator can open shift schedule panel and switch tabs | C20: 1. Click the floating shift button. 2. Switch "Đang trực" and "Sắp tới" tabs. 3. Drag panel position and close panel. | D20: Shift panel opens, tab counts are correct, drag works, and close action hides panel. | E20: Operator dashboard loaded with shift assignments data. | F20: Passed | H20: DuongNM | I20: Passed | K20: TrungDN | L20: Passed | N20: DuongNM
A21: TC3410 | B21: Operator queue refresh actions work | C21: 1. Click "Làm mới" in incident/request queue panel and rescuer panel. 2. Observe loading and updated data. | D21: Loading states show correctly and latest queue/rescuer data is rendered. | E21: Operator dashboard is open. | F21: Passed | H21: DuongNM | I21: Passed | K21: TrungDN | L21: Passed | N21: DuongNM
A22: TC3411 | B22: Operator can open incident detail from queue/map | C22: 1. Click an incident from map or queue list. 2. Verify detail modal content. | D22: Incident detail modal opens with status, user info, symptoms, media, and mission/dispatch history sections. | E22: At least one incident exists. | F22: Passed | H22: DuongNM | I22: Passed | K22: TrungDN | L22: Passed | N22: DuongNM
A23: TC3412 | B23: Operator can open catching request detail from queue/map | C23: 1. Click a catching request from map or queue list. 2. Verify detail modal content. | D23: Request detail modal opens with status, user info, species details, media, and action area. | E23: At least one snake-catching request exists. | F23: Passed | H23: DuongNM | I23: Passed | K23: TrungDN | L23: Passed | N23: DuongNM
A24: TC3413 | B24: Role guard redirects unauthorized role | C24: 1. Attempt to open Admin route with non-Admin account. 2. Attempt to open Operator route with non-Operator account. | D24: The message appeared: "Role bạn chọn không thể đăng nhập bằng tài khoản này. " | E24: Valid account exists with role mismatch for each route. | F24: Passed | H24: KhoaPA | I24: Passed | K24: TrungDN | L24: Passed | N24: TrungDN

Sheet Staff Workshifts Management
A2: Feature | B2: Staff Workshifts Management | R2: Passed
A3: Test requirement | B3: Verify shift templates, assignment operations, check-in/check-out, and scheduling window navigation for rescue staff management. | R3: Failed
A4: Number of TCs | B4: =COUNTA(A12:A13)+COUNTA(A15:A16)+COUNTA(A18)+COUNTA(A20)+COUNTA(A22:A27) -> 12 | R4: Pending
A5: Testing Round | B5: Passed | C5: Failed | D5: Pending | E5: N/A | R5: N/A
A6: Round 1 | B6: =COUNTIF($F10:$F991,B5) -> 12 | C6: =COUNTIF($F10:$F991,C5) -> 0 | D6: =COUNTIF($F10:$F991,D5) -> 0 | E6: =COUNTIF($F10:$F991,E5) -> 0
A7: Round 2 | B7: =COUNTIF($I10:$I991,B5) -> 12 | C7: =COUNTIF($I10:$I991,C5) -> 0 | D7: =COUNTIF($I10:$I991,D5) -> 0 | E7: =COUNTIF($I10:$I991,E5) -> 0
A8: Round 3 | B8: =COUNTIF($L10:$L991,B5) -> 12 | C8: =COUNTIF($L10:$L991,C5) -> 0 | D8: =COUNTIF($L10:$L991,D5) -> 0 | E8: =COUNTIF($L10:LF991,E5) -> 0
A10: Test Case ID | B10: Test Case Description | C10: Test Case Procedure | D10: Expected Results | E10: Pre-conditions | F10: Round 1 | G10: Test date | H10: Tester | I10: Round 2 | J10: Test date | K10: Tester | L10: Round 3 | M10: Test date | N10: Tester | O10: Note
A11: List Workshifts
A12: TC3501 | B12: Workshifts page opens and loads baseline data | C12: 1. Sign in as Admin. 2. Open "Quản lý lịch làm việc" page. | D12: Shift templates, assignment grid, rescuer registry, and today assignment snapshot load successfully. | E12: Admin account is active; workshift/operator APIs are available. | F12: Passed | H12: KhoaPA | I12: Passed | K12: DuongNM | L12: Passed | N12: KhoaPA
A13: TC3502 | B13: Date window navigation by 7 days works | C13: 1. On "Quản lý lịch làm việc" page, click "Lùi 7 ngày" and "Tới 7 ngày". 2. Verify assignment grid refresh. | D13: WindowStartDate changes correctly and assignments reload for new date range. | E13: Workshifts page loaded. | F13: Passed | H13: KhoaPA | I13: Passed | K13: DuongNM | L13: Passed | N13: KhoaPA
A14: Create Workshifts
A15: TC3503 | B15: Create shift template success | C15: 1. Click "Thêm mẫu ca". 2. Enter valid name/time/required rescuers. 3. Click "Tạo mới". | D15: New shift is created and appears in shift list/grid. | E15: No conflicting validation issues from backend. | F15: Passed | H15: KhoaPA | I15: Passed | K15: DuongNM | L15: Passed | N15: KhoaPA
A16: TC3504 | B16: Create shift validation blocks invalid payload | C16: 1. Open "Thêm mẫu ca" modal. 2. Leave required fields empty or send invalid values. 3. Click "Tạo mới". | D16: Save is blocked or API validation message is shown in UI error area. | E16: Workshift form is opened. | F16: Passed | H16: KhoaPA | I16: Passed | K16: DuongNM | L16: Passed | N16: KhoaPA
A17: Edit Workshifts
A18: TC3505 | B18: Update shift template success | C18: 1. Select an existing shift and click "Sửa". 2. Update time, required rescuers, or active flag. 3. Click "Lưu thay đổi". | D18: Shift is updated and reflected in schedule view. | E18: At least one shift exists. | F18: Passed | H18: KhoaPA | I18: Passed | K18: DuongNM | L18: Passed | N18: KhoaPA
A19: Delete Workshifts
A20: TC3506 | B20: Delete shift template success | C20: 1. Select a shift. 2. Click "Xóa" and confirm. | D20: Shift is deleted (soft delete behavior) and removed from active list. | E20: At least one shift exists and user confirms deletion. | F20: Passed | H20: KhoaPA | I20: Passed | K20: DuongNM | L20: Passed | N20: KhoaPA
A21: Manage Workshift Assignments
A22: TC3507 | B22: Open assignment modal for a shift-day cell | C22: 1. Click one assignment cell and open "Chi tiết" in date grid. 2. Observe existing assignments and forms. | D22: Assignment modal opens with seeded drafts for existing assignments and add controls. | E22: At least one active shift exists. | F22: Passed | H22: KhoaPA | I22: Passed | K22: DuongNM | L22: Passed | N22: KhoaPA
A23: TC3508 | B23: Assign one rescuer into shift | C23: 1. In assignment modal, choose one rescuer and optional note. 2. Click "Gán 1 cứu hộ viên". | D23: Single assignment is created and appears in the cell. | E23: Selected cell has available rescuer not yet assigned. | F23: Passed | H23: KhoaPA | I23: Passed | K23: DuongNM | L23: Passed | N23: KhoaPA
A24: TC3509 | B24: Bulk assign multiple rescuers | C24: 1. In assignment modal, choose multiple rescuers. 2. Click "Gán hàng loạt". | D24: Multiple assignments are created and reflected in the selected cell. | E24: Selected cell supports multiple assignments. | F24: Passed | H24: KhoaPA | I24: Passed | K24: DuongNM | L24: Passed | N24: KhoaPA
A25: TC3510 | B25: Update assignment status/date/notes | C25: 1. Edit assignment fields in modal. 2. Click "Lưu". | D25: Assignment data is updated with selected status/date/notes. | E25: At least one assignment exists. | F25: Passed | H25: KhoaPA | I25: Passed | K25: DuongNM | L25: Passed | N25: KhoaPA
A26: TC3511 | B26: Delete assignment success | C26: 1. Click "Xóa" on an assignment row. 2. Confirm deletion. | D26: Assignment is removed from the schedule cell. | E26: At least one assignment exists. | F26: Passed | H26: KhoaPA | I26: Passed | K26: DuongNM | L26: Passed | N26: KhoaPA
A27: TC3512 | B27: Rescuer detail view in assignment flow | C27: 1. Open assignment modal from "Chi tiết" action. 2. Click "Hồ sơ" for an assigned rescuer. | D27: Rescuer detail loads and displays profile/contact/status data. | E27: At least one assigned rescuer exists in selected cell. | F27: Passed | H27: KhoaPA | I27: Passed | K27: DuongNM | L27: Passed | N27: KhoaPA

Sheet Users Account & Role Management
A2: Feature | B2: Users Account & Role Management | R2: Passed
A3: Test requirement | B3: Verify admin user list/search/filter, detail view, user stats, and account lock/unlock operations. | R3: Failed
A4: Number of TCs | B4: =COUNTA(A12:A993) -> 7 | R4: Pending
A5: Testing Round | B5: Passed | C5: Failed | D5: Pending | E5: N/A | R5: N/A
A6: Round 1 | B6: =COUNTIF($F10:$F991,B5) -> 7 | C6: =COUNTIF($F10:$F991,C5) -> 0 | D6: =COUNTIF($F10:$F991,D5) -> 0 | E6: =COUNTIF($F10:$F991,E5) -> 0
A7: Round 2 | B7: =COUNTIF($I10:$I991,B5) -> 7 | C7: =COUNTIF($I10:$I991,C5) -> 0 | D7: =COUNTIF($I10:$I991,D5) -> 0 | E7: =COUNTIF($I10:$I991,E5) -> 0
A8: Round 3 | B8: =COUNTIF($L10:$L991,B5) -> 7 | C8: =COUNTIF($L10:$L991,C5) -> 0 | D8: =COUNTIF($L10:$L991,D5) -> 0 | E8: =COUNTIF($L10:$L991,E5) -> 0
A10: Test Case ID | B10: Test Case Description | C10: Test Case Procedure | D10: Expected Results | E10: Pre-conditions | F10: Round 1 | G10: Test date | H10: Tester | I10: Round 2 | J10: Test date | K10: Tester | L10: Round 3 | M10: Test date | N10: Tester | O10: Note
A11: Users Account & Role Management
A12: TC3601 | B12: Users page loads list and stats | C12: 1. Sign in as Admin. 2. Open "Quản lý người dùng" page. | D12: User list table and stats cards/chart are displayed. | E12: Admin account is active; user/analytics APIs are available. | F12: Passed | H12: KhoaPA | I12: Passed | K12: TrungDN | L12: Passed | N12: KhoaPA
A13: TC3602 | B13: User filtering and search | C13: 1. Apply role filter, active status filter, and keyword search. 2. Observe list updates. | D13: List updates according to filters; pagination resets to first page when filter changes. | E13: User dataset contains mixed roles/statuses. | F13: Passed | H13: KhoaPA | I13: Passed | K13: TrungDN | L13: Passed | N13: KhoaPA
A14: TC3603 | B14: User pagination and page-size control | C14: 1. Change page and page size. 2. Verify rows and page indicators. | D14: Correct page data is loaded and page controls remain consistent. | E14: Total users exceed one page. | F14: Passed | H14: KhoaPA | I14: Passed | K14: TrungDN | L14: Passed | N14: KhoaPA
A15: TC3604 | B15: Open user detail | C15: 1. Click "Chi tiết" on any row. | D15: Detail modal shows profile, account status, reputation, timestamps, and role-specific data if available. | E15: At least one user exists. | F15: Passed | H15: KhoaPA | I15: Passed | K15: TrungDN | L15: Passed | N15: KhoaPA
A16: TC3605 | B16: Ban user with required reason | C16: 1. Click "Khóa" on an active user. 2. Submit without reason, then with reason. | D16: Empty reason is blocked; valid reason bans user and list/detail refreshes. | E16: At least one active user exists. | F16: Passed | H16: KhoaPA | I16: Passed | K16: TrungDN | L16: Passed | N16: KhoaPA
A17: TC3606 | B17: Unban locked user | C17: 1. Click "Mở khóa" on a locked user. | D17: User is unlocked and refreshed data shows active status. | E17: At least one locked user exists. | F17: Passed | H17: KhoaPA | I17: Passed | K17: TrungDN | L17: Passed | N17: KhoaPA
A18: TC3607 | B18: API/validation errors surface correctly | C18: 1. Simulate list/detail/ban/unban API error. | D18: Error toast and inline message are shown; page remains usable. | E18: Test environment can simulate API errors. | F18: Passed | H18: KhoaPA | I18: Passed | K18: TrungDN | L18: Passed | N18: KhoaPA

Sheet Request Management
A2: Feature | B2: Request Management | R2: Passed
A3: Test requirement | B3: Verify Admin list/detail oversight and Operator action workflows for incidents and snake-catching requests, plus consultation booking management list/detail flows. | R3: Failed
A4: Number of TCs | B4: =COUNTA(A12:A992) -> 19 | R4: Pending
A5: Testing Round | B5: Passed | C5: Failed | D5: Pending | E5: N/A | R5: N/A
A6: Round 1 | B6: =COUNTIF($F10:$F990,B5) -> 19 | C6: =COUNTIF($F10:$F990,C5) -> 0 | D6: =COUNTIF($F10:$F990,D5) -> 0 | E6: =COUNTIF($F10:$F990,E5) -> 0
A7: Round 2 | B7: =COUNTIF($I10:$I990,B5) -> 19 | C7: =COUNTIF($I10:$I990,C5) -> 0 | D7: =COUNTIF($I10:$I990,D5) -> 0 | E7: =COUNTIF($I10:$I990,E5) -> 0
A8: Round 3 | B8: =COUNTIF($L10:$L990,B5) -> 19 | C8: =COUNTIF($L10:$L990,C5) -> 0 | D8: =COUNTIF($L10:$L990,D5) -> 0 | E8: =COUNTIF($L10:$L990,E5) -> 0
A10: Test Case ID | B10: Test Case Description | C10: Test Case Procedure | D10: Expected Results | E10: Pre-conditions | F10: Round 1 | G10: Test date | H10: Tester | I10: Round 2 | J10: Test date | K10: Tester | L10: Round 3 | M10: Test date | N10: Tester | O10: Note
A11: Request Management
A12: TC3701 | B12: Admin incidents tab list loads | C12: 1. Open "Quản lý sự cố" page. 2. Keep "Incidents" tab active. | D12: Incident list renders with status badges, mission columns, and pagination. | E12: Admin account is active; incidents API available. | F12: Passed | H12: KhoaPA | I12: Passed | K12: TrungDN | L12: Passed | N12: KhoaPA
A13: TC3702 | B13: Admin incidents filters by status/date | C13: 1. Set status and from/to date filters. 2. Change page size/page. | D13: List is filtered server-side and pagination metadata is updated correctly. | E13: Incident data exists across multiple statuses/dates. | F13: Passed | H13: KhoaPA | I13: Passed | K13: TrungDN | L13: Passed | N13: KhoaPA
A14: TC3703 | B14: Admin incident detail opens from list | C14: 1. Click "Chi tiết" on an incident row. | D14: Detail modal shows severity, user/location, symptoms, media, identified snake info, and mission history. | E14: At least one incident exists. | F14: Passed | H14: KhoaPA | I14: Passed | K14: TrungDN | L14: Passed | N14: KhoaPA
A15: TC3704 | B15: Admin missions tab list and detail | C15: 1. Switch to Missions tab. 2. Filter by mission status/date. 3. Open mission detail. | D15: Missions list and detail modal load with cost fields, mission status timeline, and linked incident data. | E15: Mission records exist. | F15: Passed | H15: KhoaPA | I15: Passed | K15: TrungDN | L15: Passed | N15: KhoaPA
A16: TC3705 | B16: Admin incidents page handles empty/error states | C16: 1. Use filters yielding no data. 2. Simulate API failure for incidents or missions. | D16: Correct no-data placeholder and error toast/message appear without page crash. | E16: Test environment supports empty result and API error simulation. | F16: Passed | H16: KhoaPA | I16: Passed | K16: TrungDN | L16: Passed | N16: KhoaPA
A17: TC3706 | B17: Operator confirms pending incident | C17: 1. Open pending incident alert or incident detail. 2. Click "Xác minh" or "Xác nhận case". | D17: Incident transitions from Pending to verified flow and queue updates in dashboard. | E17: Operator has pending incident. | F17: Passed | H17: DuongNM | I17: Passed | K17: TrungDN | L17: Passed | N17: DuongNM
A18: TC3707 | B18: Operator marks false alarm from pending incident | C18: 1. Open pending incident detail. 2. Click "Báo động giả". | D18: Incident is marked false alarm and removed from active handling queue. | E18: Operator has pending incident eligible for false alarm action. | F18: Passed | H18: DuongNM | I18: Passed | K18: TrungDN | L18: Passed | N18: DuongNM
A19: TC3708 | B19: Operator dispatches rescuer from verified incident | C19: 1. Open verified incident detail. 2. Click "Điều phối đội cứu hộ" and pick rescuer. | D19: Dispatch request is created and dispatch history updates. | E19: Verified incident exists; rescuer available. | F19: Passed | H19: DuongNM | I19: Passed | K19: TrungDN | L19: Passed | N19: DuongNM
A20: TC3709 | B20: Operator cancels pending dispatch request | C20: 1. In incident detail dispatch history, choose a Pending request. 2. Click "Hủy yêu cầu". | D20: Dispatch request status is updated and history reloads. | E20: Incident has at least one pending dispatch request. | F20: Passed | H20: DuongNM | I20: Passed | K20: TrungDN | L20: Passed | N20: DuongNM
A21: TC3710 | B21: Operator handles rescuer-aborted incident alert | C21: 1. Simulate rescuer abort event. 2. Use View detail or Redispatch action from alert. | D21: Alert appears, related incident is focused, and redispatch workflow can continue. | E21: SignalR/event feed is available. | F21: Passed | H21: DuongNM | I21: Passed | K21: TrungDN | L21: Passed | N21: DuongNM
A22: TC3711 | B22: Admin snake-catching list loads and searches | C22: 1. Open "Quản lý yêu cầu bắt rắn" page. 2. Search by id/requester/address/status. | D22: Filtered list updates correctly and rows remain clickable. | E22: Request dataset contains searchable fields. | F22: Passed | H22: KhoaPA | I22: Passed | K22: TrungDN | L22: Passed | N22: KhoaPA
A23: TC3712 | B23: Admin snake-catching detail from list | C23: 1. Click "Chi tiết" on a request row. | D23: Detail modal shows request core info, user, assigned rescuer, species details, coordinates, and media. | E23: At least one request exists. | F23: Passed | H23: KhoaPA | I23: Passed | K23: TrungDN | L23: Passed | N23: KhoaPA
... A30: TC3719 | B30: Consultation list/detail empty and error handling | C30: 1. Apply filters returning zero rows. 2. Simulate detail API failure. | D30: No-data state or detail error message appears; page remains functional. | E30: Test environment supports empty data and API error simulation. | F30: Passed | H30: KhoaPA | I30: Passed | K30: TrungDN | L30: Passed | N30: KhoaPA

Sheet Snakes Species Management
A2: Feature | B2: Snakes Species Management | R2: Passed
A3: Test requirement | B3: Verify snake species list/detail, full CRUD, media upload, and region distribution mapping workflows. | R3: Failed
A4: Number of TCs | B4: =COUNTA(A12:A13)+COUNTA(A15:A18)+COUNTA(A20:A21)+COUNTA(A23:A24) -> 10 | R4: Pending
A5: Testing Round | B5: Passed | C5: Failed | D5: Pending | E5: N/A | R5: N/A
A6: Round 1 | B6: =COUNTIF($F10:$F988,B5) -> 10 | C6: =COUNTIF($F10:$F988,C5) -> 0 | D6: =COUNTIF($F10:$F988,D5) -> 0 | E6: =COUNTIF($F10:$F988,E5) -> 0
A7: Round 2 | B7: =COUNTIF($I10:$I988,B5) -> 10 | C7: =COUNTIF($I10:$I988,C5) -> 0 | D7: =COUNTIF($I10:$I988,D5) -> 0 | E7: =COUNTIF($I10:$I988,E5) -> 0
A8: Round 3 | B8: =COUNTIF($L10:$L988,B5) -> 10 | C8: =COUNTIF($L10:$L988,C5) -> 0 | D8: =COUNTIF($L10:$L988,D5) -> 0 | E8: =COUNTIF($L10:LF988,E5) -> 0
A10: Test Case ID | B10: Test Case Description | C10: Test Case Procedure | D10: Expected Results | E10: Pre-conditions | F10: Round 1 | G10: Test date | H10: Tester | I10: Round 2 | J10: Test date | K10: Tester | L10: Round 3 | M10: Test date | N10: Tester | O10: Note
A11: List Snakes Species
A12: TC3801 | B12: Snake species list and detail load | C12: 1. Open "Quản lý loài rắn" page. 2. Select a snake species from left list. | D12: Detail panel loads with profile, risk, symptoms, first aid, venom/antivenom info, and map distribution. | E12: Snake species data exists. | F12: Passed | H12: KhoaPA | I12: Passed | K12: DuongNM | L12: Passed | N12: KhoaPA
A13: TC3802 | B13: Map/mapping reload behavior | C13: 1. Click "Làm mới" mapping action. 2. Observe loading and final map state. | D13: Loading indicator appears and latest mapping data is synced to map panel. | E13: Selected species has mapping source data. | F13: Passed | H13: KhoaPA | I13: Passed | K13: DuongNM | L13: Passed | N13: KhoaPA
A14: Create Snake Species
A15: TC3803 | B15: Create snake species success | C15: 1. Click "Thêm loài rắn". 2. Enter valid required fields and save. | D15: New species is created, appears in list, and detail can be opened. | E15: Valid admin session; create permission enabled. | F15: Passed | H15: KhoaPA | I15: Passed | K15: DuongNM | L15: Passed | N15: KhoaPA
A16: TC3804 | B16: Snake form validation and API error handling | C16: 1. Submit missing/invalid values in create or update modal. | D16: Validation error message is shown; invalid submission is not persisted. | E16: Snake upsert modal is open. | F16: Passed | H16: KhoaPA | I16: Passed | K16: DuongNM | L16: Passed | N16: KhoaPA
A17: TC3805 | B17: Upload snake media in form | C17: 1. In upsert modal, upload an image through media upload action. 2. Save form. | D17: Uploaded media id/url is bound to species and image displays in detail view. | E17: Media upload API is available. | F17: Passed | H17: KhoaPA | I17: Passed | K17: DuongNM | L17: Passed | N17: KhoaPA
A18: TC3806 | B18: Create region mapping for species | C18: 1. Click an unmapped region on map. 2. Fill common level/priority/notes and save. | D18: Mapping is created and region style/tooltip updates on map. | E18: Selected species exists; geographic regions loaded. | F18: Passed | H18: KhoaPA | I18: Passed | K18: DuongNM | L18: Passed | N18: KhoaPA
A19: Edit Snake Species
A20: TC3807 | B20: Update snake species success | C20: 1. Select a species. 2. Click "Sửa". 3. Change fields and save. | D20: Species details are updated and reflected on list/detail/map sections. | E20: At least one snake species exists. | F20: Passed | H20: KhoaPA | I20: Passed | K20: DuongNM | L20: Passed | N20: KhoaPA
A21: TC3808 | B21: Update region mapping for species | C21: 1. Click a mapped region. 2. Update common level/priority/isActive/notes and save. | D21: Mapping updates and map visualization reflects new distribution settings. | E21: Region mapping already exists for selected species. | F21: Passed | H21: KhoaPA | I21: Passed | K21: DuongNM | L21: Passed | N21: KhoaPA
A22: Delete Snake Species
A23: TC3809 | B23: Delete snake species success | C23: 1. Select a species. 2. Click "Xóa" and confirm. | D23: Species is removed and list/detail selection updates accordingly. | E23: At least one removable species exists. | F23: Passed | H23: KhoaPA | I23: Passed | K23: DuongNM | L23: Passed | N23: KhoaPA
A24: TC3810 | B24: Delete region mapping for species | C24: 1. Open mapped region dialog. 2. Delete mapping. | D24: Region mapping is removed and region reverts to unmapped style. | E24: Region mapping exists for selected species. | F24: Passed | H24: KhoaPA | I24: Passed | K24: DuongNM | L24: Passed | N24: KhoaPA

Sheet Antivenoms Inventory & Manageme
A2: Feature | B2: Antivenoms Inventory & Management | R2: Passed
A3: Test requirement | B3: Verify antivenom list/detail and CRUD operations with validation and error handling. | R3: Failed
A4: Number of TCs | B4: =COUNTA(A12:A13)+COUNTA(A15:A16)+COUNTA(A18)+COUNTA(A20) -> 6 | R4: Pending
A5: Testing Round | B5: Passed | C5: Failed | D5: Pending | E5: N/A | R5: N/A
A6: Round 1 | B6: =COUNTIF($F10:$F984,B5) -> 6 | C6: =COUNTIF($F10:$F984,C5) -> 0 | D6: =COUNTIF($F10:$F984,D5) -> 0 | E6: =COUNTIF($F10:$F984,E5) -> 0
A7: Round 2 | B7: =COUNTIF($I10:$I984,B5) -> 6 | C7: =COUNTIF($I10:$I984,C5) -> 0 | D7: =COUNTIF($I10:$I984,D5) -> 0 | E7: =COUNTIF($I10:$I984,E5) -> 0
A8: Round 3 | B8: =COUNTIF($L10:$L984,B5) -> 6 | C8: =COUNTIF($L10:$L984,C5) -> 0 | D8: =COUNTIF($L10:$L984,D5) -> 0 | E8: =COUNTIF($L10:LF984,E5) -> 0
A10: Test Case ID | B10: Test Case Description | C10: Test Case Procedure | D10: Expected Results | E10: Pre-conditions | F10: Round 1 | G10: Test date | H10: Tester | I10: Round 2 | J10: Test date | K10: Tester | L10: Round 3 | M10: Test date | N10: Tester | O10: Note
A11: List Antivenoms
A12: TC3901 | B12: Antivenoms list and detail load | C12: 1. Open "Quản lý huyết thanh" page. 2. Select an item from list. | D12: Antivenom detail (name/manufacturer/description) is displayed correctly. | E12: Antivenom data exists. | F12: Passed | H12: KhoaPA | I12: Passed | K12: DuongNM | L12: Passed | N12: KhoaPA
A13: TC3902 | B13: Load/reload error handling | C13: 1. Simulate list/detail API failure. 2. Click "Làm mới". | D13: Error messages/toasts are displayed and user can retry. | E13: Error simulation available. | F13: Passed | H13: KhoaPA | I13: Passed | K13: DuongNM | L13: Passed | N13: KhoaPA
A14: Create Antivenoms
A15: TC3903 | B15: Create antivenom success | C15: 1. Click "Thêm huyết thanh". 2. Input valid data and save. | D15: New antivenom appears in list and detail panel. | E15: Valid admin session and create permission. | F15: Passed | H15: KhoaPA | I15: Passed | K15: DuongNM | L15: Passed | N15: KhoaPA
A16: TC3904 | B16: Antivenom form validation | C16: 1. Submit missing required values (for example empty name). | D16: Validation error is shown; save does not proceed. | E16: Upsert modal is open. | F16: Passed | H16: KhoaPA | I16: Passed | K16: DuongNM | L16: Passed | N16: KhoaPA
A17: Edit Antivenoms
A18: TC3905 | B18: Update antivenom success | C18: 1. Select an antivenom. 2. Click "Cập nhật" and save modified values. | D18: Updated data is reflected in list/detail. | E18: At least one antivenom exists. | F18: Passed | H18: KhoaPA | I18: Passed | K18: DuongNM | L18: Passed | N18: KhoaPA
A19: Delete Antivenoms
A20: TC3906 | B20: Delete antivenom success | C20: 1. Select an antivenom. 2. Click "Xóa" and confirm. | D20: Antivenom is removed from list and detail panel resets. | E20: At least one removable antivenom exists. | F20: Passed | H20: KhoaPA | I20: Passed | K20: DuongNM | L20: Passed | N20: KhoaPA

Sheet Treatment Facilities Database M
A2: Feature | B2: Treatment Facilities Database Management | R2: Passed
A3: Test requirement | B3: Verify treatment facility list/detail and CRUD operations including antivenom linkage and location data. | R3: Failed
A4: Number of TCs | B4: =COUNTA(A12:A14)+COUNTA(A16:A18)+COUNTA(A20)+COUNTA(A22) -> 8 | R4: Pending
A5: Testing Round | B5: Passed | C5: Failed | D5: Pending | E5: N/A | R5: N/A
A6: Round 1 | B6: =COUNTIF($F10:$F986,B5) -> 8 | C6: =COUNTIF($F10:$F986,C5) -> 0 | D6: =COUNTIF($F10:$F986,D5) -> 0 | E6: =COUNTIF($F10:$F986,E5) -> 0
A7: Round 2 | B7: =COUNTIF($I10:$I986,B5) -> 8 | C7: =COUNTIF($I10:$I986,C5) -> 0 | D7: =COUNTIF($I10:$I986,D5) -> 0 | E7: =COUNTIF($I10:$I986,E5) -> 0
A8: Round 3 | B8: =COUNTIF($L10:$L986,B5) -> 8 | C8: =COUNTIF($L10:$L986,C5) -> 0 | D8: =COUNTIF($L10:$L986,D5) -> 0 | E8: =COUNTIF($L10:LF986,E5) -> 0
A10: Test Case ID | B10: Test Case Description | C10: Test Case Procedure | D10: Expected Results | E10: Pre-conditions | F10: Round 1 | G10: Test date | H10: Tester | I10: Round 2 | J10: Test date | K10: Tester | L10: Round 3 | M10: Test date | N10: Tester | O10: Note
A11: List Antivenoms
A12: TC4001 | B12: Facilities list and detail load | C12: 1. Open "Quản lý cơ sở điều trị" page. 2. Select a facility in list. | D12: Detail panel shows name, address, contact, coordinates, and linked antivenoms. | E12: Facility data exists. | F12: Passed | H12: KhoaPA | I12: Passed | K12: DuongNM | L12: Passed | N12: KhoaPA
A13: TC4002 | B13: Linked antivenom labels resolve correctly | C13: 1. Open facility detail with linked antivenom ids. | D13: Detail shows human-readable antivenom names. | E13: Facility has one or more linked antivenom ids. | F13: Passed | H13: KhoaPA | I13: Passed | K13: DuongNM | L13: Passed | N13: KhoaPA
A14: TC4003 | B14: Reload and API fallback behavior | C14: 1. Click "Làm mới". 2. Simulate endpoint variations/failure in treatment-facility API. | D14: Page reloads data when available and surfaces errors gracefully when failing. | E14: Test environment supports endpoint/error simulation. | F14: Passed | H14: KhoaPA | I14: Passed | K14: DuongNM | L14: Passed | N14: KhoaPA
A15: Create Antivenoms
A16: TC4004 | B16: Create treatment facility success | C16: 1. Click "Thêm cơ sở điều trị". 2. Fill valid fields including coordinates and linked antivenoms. 3. Save. | D16: New facility is created and visible in list/detail. | E16: Admin session active; antivenom options loaded. | F16: Passed | H16: KhoaPA | I16: Passed | K16: DuongNM | L16: Passed | N16: KhoaPA
A17: TC4005 | B17: Facility form validation | C17: 1. Submit invalid payload (missing name/address, invalid coordinates, invalid contact). | D17: Validation error is shown; invalid record is not saved. | E17: Upsert modal is open. | F17: Passed | H17: KhoaPA | I17: Passed | K17: DuongNM | L17: Passed | N17: KhoaPA
A18: TC4006 | B18: Antivenom options load for form selection | C18: 1. Open create/update modal. | D18: Antivenom options are available for multi-selection in form. | E18: Antivenom API is available. | F18: Passed | H18: KhoaPA | I18: Passed | K18: DuongNM | L18: Passed | N18: KhoaPA
A19: Edit Antivenoms
A20: TC4007 | B20: Update treatment facility success | C20: 1. Select a facility. 2. Click "Cập nhật" and modify fields. 3. Save. | D20: Updated values persist and reflect in detail panel. | E20: At least one facility exists. | F20: Passed | H20: KhoaPA | I20: Passed | K20: DuongNM | L20: Passed | N20: KhoaPA
A21: Delete Antivenoms
A22: TC4008 | B22: Delete treatment facility success | C22: 1. Select a facility. 2. Click "Xóa" and confirm. | D22: Facility is deleted and removed from active list. | E22: At least one removable facility exists. | F22: Passed | H22: KhoaPA | I22: Passed | K22: DuongNM | L22: Passed | N22: KhoaPA

Sheet Finance Transactions & Withdraw
A2: Feature | B2: Finance: Transactions & Withdrawals Management | R2: Passed
A3: Test requirement | B3: Verify transaction monitoring (list/detail/filter) and withdrawal processing workflows with status-gated actions. | R3: Failed
A4: Number of TCs | B4: =COUNTA(A12:A985) -> 12 | R4: Pending
A5: Testing Round | B5: Passed | C5: Failed | D5: Pending | E5: N/A | R5: N/A
A6: Round 1 | B6: =COUNTIF($F10:$F983,B5) -> 12 | C6: =COUNTIF($F10:$F983,C5) -> 0 | D6: =COUNTIF($F10:$F983,D5) -> 0 | E6: =COUNTIF($F10:$F983,E5) -> 0
A7: Round 2 | B7: =COUNTIF($I10:$I983,B5) -> 12 | C7: =COUNTIF($I10:$I983,C5) -> 0 | D7: =COUNTIF($I10:$I983,D5) -> 0 | E7: =COUNTIF($I10:$I983,E5) -> 0
A8: Round 3 | B8: =COUNTIF($L10:$L983,B5) -> 12 | C8: =COUNTIF($L10:$L983,C5) -> 0 | D8: =COUNTIF($L10:$L983,D5) -> 0 | E8: =COUNTIF($L10:$L983,E5) -> 0
A10: Test Case ID | B10: Test Case Description | C10: Test Case Procedure | D10: Expected Results | E10: Pre-conditions | F10: Round 1 | G10: Test date | H10: Tester | I10: Round 2 | J10: Test date | K10: Tester | L10: Round 3 | M10: Test date | N10: Tester | O10: Note
A11: Finance: Transactions & Withdrawals Management
A12: TC4101 | B12: Transactions tab loads list data | C12: 1. Open "Quản lý giao dịch" page. 2. Ensure "Giao dịch hệ thống" tab is active. | D12: Transaction rows render with type, amount, username, payment method, and timestamp. | E12: Transaction data exists. | F12: Passed | H12: KhoaPA | I12: Passed | K12: TrungDN | L12: Passed | N12: TrungDN
A13: TC4102 | B13: Transactions filter and pagination | C13: 1. Filter by username and transaction type. 2. Change page/page size. | D13: List updates according to filter; pagination metadata remains consistent. | E13: Dataset includes multiple transaction types/users. | F13: Passed | H13: KhoaPA | I13: Passed | K13: TrungDN | L13: Passed | N13: TrungDN
A14: TC4103 | B14: Open transaction detail from list row | C14: 1. Click a transaction row. | D14: Detail modal opens showing id/reference/type/amount/method/description/external id/time. | E14: At least one transaction exists. | F14: Passed | H14: KhoaPA | I14: Passed | K14: TrungDN | L14: Passed | N14: TrungDN
A15: TC4104 | B15: Transactions empty and error states | C15: 1. Apply filter returning no data. 2. Simulate API failure. | D15: No-data and error states are shown correctly with recoverable UX. | E15: Environment supports empty result and error simulation. | F15: Passed | H15: KhoaPA | I15: Passed | K15: TrungDN | L15: Passed | N15: TrungDN
A16: TC4105 | B16: Withdrawals processing list and detail | C16: 1. Switch to "Duyệt rút tiền" tab. 2. Select one processing item. | D16: Detail panel shows amount, bank info, status, timeline, and admin action area. | E16: At least one withdrawal exists. | F16: Passed | H16: KhoaPA | I16: Passed | K16: TrungDN | L16: Passed | N16: TrungDN
A17: TC4106 | B17: Approve Pending withdrawal | C17: 1. Select Pending withdrawal. 2. Fill optional admin notes. 3. Click "Duyệt". | D17: Status becomes Approved and detail/list refresh successfully. | E17: Pending withdrawal exists. | F17: Passed | H17: DuongNM | I17: Passed | K17: TrungDN | L17: Passed | N17: TrungDN
A18: TC4107 | B18: Reject withdrawal requires reason | C18: 1. Select Pending/Approved withdrawal. 2. Try reject without reason, then with reason. | D18: Empty reason is blocked; valid reason rejects withdrawal and status updates. | E18: Pending or Approved withdrawal exists. | F18: Passed | H18: DuongNM | I18: Passed | K18: TrungDN | L18: Passed | N18: TrungDN
A19: TC4108 | B19: Complete Approved withdrawal | C19: 1. Select Approved withdrawal. 2. Click "Hoàn tất". | D19: Status transitions to Completed and item appears in done list. | E19: Approved withdrawal exists. | F19: Passed | H19: DuongNM | I19: Passed | K19: TrungDN | L19: Passed | N19: TrungDN
A20: TC4109 | B20: Fail Approved withdrawal requires reason | C20: 1. Select Approved withdrawal. 2. Try Fail without reason, then with reason. | D20: Empty reason is blocked; valid reason sets status Failed and refreshes list/detail. | E20: Approved withdrawal exists. | F20: Passed | H20: DuongNM | I20: Passed | K20: TrungDN | L20: Passed | N20: TrungDN
A21: TC4110 | B21: Done tab displays finalized withdrawals | C21: 1. Switch to "Đã xử lý" tab. 2. Open Rejected/Completed/Failed detail. | D21: Finalized records are displayed; action buttons become non-actionable as per status. | E21: Finalized withdrawals exist. | F21: Passed | H21: DuongNM | I21: Passed | K21: TrungDN | L21: Passed | N21: TrungDN
A22: TC4111 | B22: VietQR display and payload copy | C22: 1. Open detail of withdrawal containing VietQR data. 2. Click Copy QR payload. | D22: QR image/payload is shown when available and payload copy succeeds with toast feedback. | E22: Selected withdrawal includes vietQrImageBase64 or vietQrPayload. | F22: Passed | H22: KhoaPA | I22: Passed | K22: TrungDN | L22: Passed | N22: TrungDN
A23: TC4112 | B23: Action button availability by status | C23: 1. Open details for Pending, Approved, and finalized statuses. | D23: Buttons are shown only for valid transitions (Approve/Reject/Complete/Fail according to status). | E23: Withdrawal records across multiple statuses exist. | F23: Passed | H23: KhoaPA | I23: Passed | K23: TrungDN | L23: Passed | N23: TrungDN

Sheet Report Media Management
A2: Feature | B2: Report Media Management | R2: Passed
A3: Test requirement | B3: Verify AI recognition report media listing, multi-filtering, pagination, and detailed review visualization. | R3: Failed
A4: Number of TCs | B4: =COUNTA(A12:A978) -> 5 | R4: Pending
A5: Testing Round | B5: Passed | C5: Failed | D5: Pending | E5: N/A | R5: N/A
A6: Round 1 | B6: =COUNTIF($F10:$F976,B5) -> 5 | C6: =COUNTIF($F10:$F976,C5) -> 0 | D6: =COUNTIF($F10:$F976,D5) -> 0 | E6: =COUNTIF($F10:$F976,E5) -> 0
A7: Round 2 | B7: =COUNTIF($I10:$I976,B5) -> 5 | C7: =COUNTIF($I10:$I976,C5) -> 0 | D7: =COUNTIF($I10:$I976,D5) -> 0 | E7: =COUNTIF($I10:$I976,E5) -> 0
A8: Round 3 | B8: =COUNTIF($L10:$L976,B5) -> 5 | C8: =COUNTIF($L10:$L976,C5) -> 0 | D8: =COUNTIF($L10:$L976,D5) -> 0 | E8: =COUNTIF($L10:$L976,E5) -> 0
A10: Test Case ID | B10: Test Case Description | C10: Test Case Procedure | D10: Expected Results | E10: Pre-conditions | F10: Round 1 | G10: Test date | H10: Tester | I10: Round 2 | J10: Test date | K10: Tester | L10: Round 3 | M10: Test date | N10: Tester | O10: Note
A11: Report Media Management
A12: TC4201 | B12: AI recognition list loads | C12: 1. Open "Quản lý ảnh báo cáo rắn" page. | D12: List renders with id/source/thumbnail/confidence/species/status/time columns. | E12: AI recognition data exists. | F12: Passed | H12: KhoaPA | I12: Passed | K12: DuongNM | L12: Passed | N12: TrungDN
A13: TC4202 | B13: Filter by status, source, confidence, and date range | C13: 1. Apply combinations of status, reference type, min-max confidence, and from-to date. | D13: Result list is filtered correctly and page resets as expected when filters change. | E13: Dataset includes varied status/source/confidence values. | F13: Passed | H13: KhoaPA | I13: Passed | K13: DuongNM | L13: Passed | N13: TrungDN
A14: TC4203 | B14: Pagination and page-size in AI recognition list | C14: 1. Change page and page size. | D14: Correct page data and pagination controls are displayed. | E14: Total records exceed one page. | F14: Passed | H14: KhoaPA | I14: Passed | K14: DuongNM | L14: Passed | N14: TrungDN
A15: TC4204 | B15: Open AI recognition detail from list | C15: 1. Click "Xem chi tiết" on any row. | D15: Detail modal shows media, source metadata, AI result, expert review state, and timeline fields. | E15: At least one AI recognition record exists. | F15: Passed | H15: KhoaPA | I15: Passed | K15: DuongNM | L15: Passed | N15: TrungDN
A16: TC4205 | B16: Empty and API error handling | C16: 1. Apply filters yielding no records. 2. Simulate list/detail API error. | D16: No-data and error messages are shown without breaking modal/page interactions. | E16: Error simulation available. | F16: Passed | H16: DuongNM | I16: Passed | K16: DuongNM | L16: Passed | N16: TrungDN

Sheet Portal System Settings & Config
A2: Feature | B2: Portal System Settings & Configuration | R2: Passed
A3: Test requirement | B3: Verify dynamic settings list/detail, type-specific validation, create/edit, key/all cache reload workflows, and JSON formatting helper. | R3: Failed
A4: Number of TCs | B4: =COUNTA(A12:A14)+COUNTA(A16:A19)+COUNTA(A21)+COUNTA(A23:A25) -> 11 | R4: Pending
A5: Testing Round | B5: Passed | C5: Failed | D5: Pending | E5: N/A | R5: N/A
A6: Round 1 | B6: =COUNTIF($F10:$F989,B5) -> 11 | C6: =COUNTIF($F10:$F989,C5) -> 0 | D6: =COUNTIF($F10:$F989,D5) -> 0 | E6: =COUNTIF($F10:$F989,E5) -> 0
A7: Round 2 | B7: =COUNTIF($I10:$I989,B5) -> 11 | C7: =COUNTIF($I10:$I989,C5) -> 0 | D7: =COUNTIF($I10:$I989,D5) -> 0 | E7: =COUNTIF($I10:$I989,E5) -> 0
A8: Round 3 | B8: =COUNTIF($L10:$L989,B5) -> 11 | C8: =COUNTIF($L10:$L989,C5) -> 0 | D8: =COUNTIF($L10:$L989,D5) -> 0 | E8: =COUNTIF($L10:LF989,E5) -> 0
A10: Test Case ID | B10: Test Case Description | C10: Test Case Procedure | D10: Expected Results | E10: Pre-conditions | F10: Round 1 | G10: Test date | H10: Tester | I10: Round 2 | J10: Test date | K10: Tester | L10: Round 3 | M10: Test date | N10: Tester | O10: Note
A11: List System Settings
A12: TC4301 | B12: Settings list and search | C12: 1. Open "Quản lý cấu hình động" page. 2. Search by key/value/type/description. | D12: Filtered list updates correctly and selected item detail can be opened. | E12: System setting records exist. | F12: Passed | H12: KhoaPA | I12: Passed | K12: DuongNM | L12: Passed | N12: DuongNM
A13: TC4302 | B13: Open setting detail | C13: 1. Select a setting from list. | D13: Detail panel shows key, type, description, value, created/updated timestamps; JSON values render formatted view. | E13: At least one setting exists. | F13: Passed | H13: KhoaPA | I13: Passed | K13: DuongNM | L13: Passed | N13: DuongNM
A14: TC4313 | B14: List refresh action | C14: 1. Click "Làm mới danh sách". | D14: Settings list reloads and success toast appears. | E14: Settings page opened. | F14: Passed | H14: KhoaPA | I14: Passed | K14: DuongNM | L14: Passed | N14: DuongNM
A15: Create System Settings
A16: TC4304 | B16: Create String setting success | C16: 1. Click "Tạo cấu hình". 2. Input key, String value, optional description. 3. Save. | D16: Setting is created and appears in list/detail. | E16: New unique key is available. | F16: Passed | H16: KhoaPA | I16: Passed | K16: DuongNM | L16: Passed | N16: DuongNM
A17: TC4305 | B17: Create Int/Decimal validation | C17: 1. In create modal, set valueType Int/Decimal and enter invalid then valid value. | D17: Invalid numeric value is blocked with validation message; valid value saves successfully. | E17: Create modal is open. | F17: Passed | H17: KhoaPA | I17: Passed | K17: DuongNM | L17: Passed | N17: DuongNM
A18: TC4306 | B18: Create Boolean validation and normalization | C18: 1. Set valueType Boolean. 2. Save using true/false options only. | D18: Only true/false accepted; saved value is normalized correctly. | E18: Create/edit modal is open. | F18: Passed | H18: KhoaPA | I18: Passed | K18: DuongNM | L18: Passed | N18: DuongNM
A19: TC4307 | B19: Create JSON validation and format helper | C19: 1. Set valueType Json. 2. Enter invalid JSON and save. 3. Enter valid JSON and click "Định dạng JSON" then save. | D19: Invalid JSON is blocked; valid JSON can be formatted and saved. | E19: Create/edit modal is open. | F19: Passed | H19: KhoaPA | I19: Passed | K19: DuongNM | L19: Passed | N19: DuongNM
A20: Edit System Settings
A21: TC4308 | B21: Edit setting with key read-only | C21: 1. Select an existing key and click "Chỉnh sửa". 2. Update value/description/type and save. | D21: Key cannot be changed in edit mode; other fields update successfully. | E21: Existing setting is selected. | F21: Passed | H21: KhoaPA | I21: Passed | K21: DuongNM | L21: Passed | N21: DuongNM
A22: Reload System Settings
A23: TC4309 | B23: Reload single key behavior | C23: 1. Select setting and click "Áp dụng lại cấu hình hiện tại". | D23: Key cache is reloaded; latest value appears in detail/list. | E23: Selected key exists and reloadKey API is available. | F23: Passed | H23: KhoaPA | I23: Passed | K23: DuongNM | L23: Passed | N23: DuongNM
A24: TC4310 | B24: Reload all settings behavior | C24: 1. Click "Áp dụng lại tất cả cấu hình". | D24: System reloads all keys and list/detail remains consistent after refresh. | E24: reloadAll API is available. | F24: Passed | H24: KhoaPA | I24: Passed | K24: DuongNM | L24: Passed | N24: DuongNM
A25: TC4311 | B25: Error handling on save/reload | C25: 1. Simulate API validation/server error for save and reload actions. | D25: Field errors and global error toasts/messages are shown; page remains usable. | E25: Error simulation available. | F25: Passed | H25: KhoaPA | I25: Passed | K25: DuongNM | L25: Passed | N25: DuongNM

Sheet Learning Lessons Database Manag
A2: Feature | B2: Learning: Lessons Database Management | R2: Passed
A3: Test requirement | B3: Verify lesson list/filter/search with integrated detail preview, plus full CRUD for lesson content management. | R3: Failed
A4: Number of TCs | B4: =COUNTA(A12:A16)+COUNTA(A18)+COUNTA(A20)+COUNTA(A22) -> 8 | R4: Pending
A5: Testing Round | B5: Passed | C5: Failed | D5: Pending | E5: N/A | R5: N/A
A6: Round 1 | B6: =COUNTIF($F10:$F986,B5) -> 8 | C6: =COUNTIF($F10:$F986,C5) -> 0 | D6: =COUNTIF($F10:$F986,D5) -> 0 | E6: =COUNTIF($F10:$F986,E5) -> 0
A7: Round 2 | B7: =COUNTIF($I10:$I986,B5) -> 8 | C7: =COUNTIF($I10:$I986,C5) -> 0 | D7: =COUNTIF($I10:$I986,D5) -> 0 | E7: =COUNTIF($I10:$I986,E5) -> 0
A8: Round 3 | B8: =COUNTIF($L10:$L986,B5) -> 8 | C8: =COUNTIF($L10:$L986,C5) -> 0 | D8: =COUNTIF($L10:$L986,D5) -> 0 | E8: =COUNTIF($L10:LF986,E5) -> 0
A10: Test Case ID | B10: Test Case Description | C10: Test Case Procedure | D10: Expected Results | E10: Pre-conditions | F10: Round 1 | G10: Test date | H10: Tester | I10: Round 2 | J10: Test date | K10: Tester | L10: Round 3 | M10: Test date | N10: Tester | O10: Note
A11: List Lessons
A12: TC4401 | B12: Lesson list with category/publish/search filters and detail open | C12: 1. Open "Quản lý bài học" page. 2. Apply category and publish filters. 3. Search by title. 4. Select a lesson item. | D12: Filtered list updates and selected lesson detail/preview loads in right panel. | E12: Lesson dataset exists with mixed category/status. | F12: Passed | H12: KhoaPA | I12: Passed | K12: TrungDN | L12: Passed | N12: TrungDN
A13: TC4402 | B13: Publish/draft filter behavior | C13: 1. Toggle publish filter between All, Published, Draft. | D13: List only shows lessons matching selected publish state. | E13: Dataset contains both published and draft lessons. | F13: Passed | H13: KhoaPA | I13: Passed | K13: TrungDN | L13: Passed | N13: TrungDN
A14: TC4403 | B14: Category filter counters and switching | C14: 1. Switch category tabs All/Safety/Catching/FirstAid. | D14: Counters and filtered result sets are consistent with underlying data. | E14: Lessons exist in multiple categories. | F14: Passed | H14: KhoaPA | I14: Passed | K14: TrungDN | L14: Passed | N14: TrungDN
A15: TC4404 | B15: Lesson content preview rendering | C15: 1. Open lesson detail with rich content. | D15: Preview component renders content without layout break. | E15: Lesson with rich content exists. | F15: Passed | H15: KhoaPA | I15: Passed | K15: TrungDN | L15: Passed | N15: TrungDN
A16: TC4405 | B16: Empty and API error states | C16: 1. Run filters producing no data. 2. Simulate list/detail/upsert/remove API failure. | D16: Correct empty/error states and toasts are displayed. | E16: Error simulation available. | F16: Passed | H16: KhoaPA | I16: Passed | K16: TrungDN | L16: Passed | N16: TrungDN
A17: Create Lessons
A18: TC4406 | B18: Create lesson success | C18: 1. Click "Thêm bài học". 2. Enter valid title/content/category/publish status. 3. Save. | D18: New lesson is created and can be selected from list. | E18: Admin session active. | F18: Passed | H18: KhoaPA | I18: Passed | K18: TrungDN | L18: Passed | N18: TrungDN
A19: Edit Lessons
A20: TC4407 | B20: Update lesson success | C20: 1. Select a lesson. 2. Click "Sửa". 3. Modify fields and save. | D20: Lesson detail updates with new content/category/status. | E20: At least one lesson exists. | F20: Passed | H20: KhoaPA | I20: Passed | K20: TrungDN | L20: Passed | N20: TrungDN
A21: Delete Lessons
A22: TC4408 | B22: Delete lesson success | C22: 1. Select a lesson. 2. Click "Xóa" and confirm. | D22: Lesson is removed and list/detail selection updates safely. | E22: At least one removable lesson exists. | F22: Passed | H22: KhoaPA | I22: Passed | K22: TrungDN | L22: Passed | N22: TrungDN

Sheet Content Blogs Database Manageme
A2: Feature | B2: Content: Blogs Database Management | R2: Passed
A3: Test requirement | B3: Verify blog list/detail management, full CRUD, and status workflow actions (approve/reject/publish/take-down). | R3: Failed
A4: Number of TCs | B4: =COUNTA(A12:A14)+COUNTA(A16)+COUNTA(A18)+COUNTA(A20)+COUNTA(A22:A27) -> 12 | R4: Pending
A5: Testing Round | B5: Passed | C5: Failed | D5: Pending | E5: N/A | R5: N/A
A6: Round 1 | B6: =COUNTIF($F10:$F984,B5) -> 12 | C6: =COUNTIF($F10:$F984,C5) -> 0 | D6: =COUNTIF($F10:$F984,D5) -> 0 | E6: =COUNTIF($F10:$F984,E5) -> 0
A7: Round 2 | B7: =COUNTIF($I10:$I984,B5) -> 12 | C7: =COUNTIF($I10:$I984,C5) -> 0 | D7: =COUNTIF($I10:$I984,D5) -> 0 | E7: =COUNTIF($I10:$I984,E5) -> 0
A8: Round 3 | B8: =COUNTIF($L10:$L984,B5) -> 12 | C8: =COUNTIF($L10:$L984,C5) -> 0 | D8: =COUNTIF($L10:$L984,D5) -> 0 | E8: =COUNTIF($L10:LF984,E5) -> 0
A10: Test Case ID | B10: Test Case Description | C10: Test Case Procedure | D10: Expected Results | E10: Pre-conditions | F10: Round 1 | G10: Test date | H10: Tester | I10: Round 2 | J10: Test date | K10: Tester | L10: Round 3 | M10: Test date | N10: Tester | O10: Note
A11: List Blogs
A12: TC4501 | B12: Blog list loads with status tabs and search | C12: 1. Open "Quản lý bài viết" page. 2. Switch status tabs. 3. Search by title/author. | D12: List updates by selected status/search; row counts per tab are consistent. | E12: Blog records exist with multiple statuses. | F12: Passed | H12: TrungDN | I12: Passed | K12: KhoaPA | L12: Passed | N12: TrungDN
A13: TC4502 | B13: Open blog detail from list | C13: 1. Select a blog item in left panel. | D13: Detail area shows status/category/tags/author/stats/preview and optional thumbnail sidebar. | E13: At least one blog exists. | F13: Passed | H13: TrungDN | I13: Passed | K13: KhoaPA | L13: Passed | N13: TrungDN
A14: TC4503 | B14: Tag/category/status metadata display consistency | C14: 1. Open detail of blogs with different tags/categories/statuses. | D14: Labels/badges match configured enums and remain consistent between list and detail. | E14: Dataset contains varied categories/tags/statuses. | F14: Passed | H14: TrungDN | I14: Passed | K14: KhoaPA | L14: Passed | N14: TrungDN
A15: Create Blogs
A16: TC4504 | B16: Create blog (draft or published) | C16: 1. Click "Tạo bài". 2. Fill required fields and choose status. 3. Save. | D16: Blog is created with selected status and appears in list/detail. | E16: Admin session active. | F16: Passed | H16: TrungDN | I16: Passed | K16: KhoaPA | L16: Passed | N16: TrungDN
A17: Edit Blogs
A18: TC4505 | B18: Update blog success | C18: 1. Open blog detail. 2. Click "Sửa". 3. Modify content/metadata and save. | D18: Blog content and metadata update successfully in detail and list. | E18: At least one editable blog exists. | F18: Passed | H18: TrungDN | I18: Passed | K18: KhoaPA | L18: Passed | N18: TrungDN
A19: Delete Blogs
A20: TC4506 | B20: Delete blog success | C20: 1. Open blog detail. 2. Click "Xóa" and confirm. | D20: Blog is deleted and removed from list. | E20: At least one removable blog exists. | F20: Passed | H20: TrungDN | I20: Passed | K20: KhoaPA | L20: Passed | N20: TrungDN
A21: Moderate Blog Workflow
A22: TC4507 | B22: Approve pending blog | C22: 1. Open blog with PendingApproval status. 2. Click "Duyệt". | D22: Status changes to Published and action feedback is shown. | E22: PendingApproval blog exists. | F22: Passed | H22: TrungDN | I22: Passed | K22: KhoaPA | L22: Passed | N22: TrungDN
A23: TC4508 | B23: Reject pending blog with reason | C23: 1. Open PendingApproval blog. 2. Open reject form. 3. Enter reason and confirm reject. | D23: Blog status becomes Rejected and rejection reason is shown in detail. | E23: PendingApproval blog exists. | F23: Passed | H23: TrungDN | I23: Passed | K23: KhoaPA | L23: Passed | N23: TrungDN
A24: TC4509 | B24: Approve rejected blog | C24: 1. Open Rejected blog. 2. Click "Duyệt luôn". | D24: Blog transitions to Published and status badge updates. | E24: Rejected blog exists. | F24: Passed | H24: TrungDN | I24: Passed | K24: KhoaPA | L24: Passed | N24: TrungDN
A25: TC45010 | B25: Take down published blog | C25: 1. Open Published blog. 2. Click "Gỡ xuống" and confirm. | D25: Blog transitions from Published to Draft. | E25: Published blog exists. | F25: Passed | H25: TrungDN | I25: Passed | K25: KhoaPA | L25: Passed | N25: TrungDN
A26: TC4511 | B26: Publish draft directly | C26: 1. Open Draft blog. 2. Click "Đăng ngay". | D26: Blog transitions from Draft to Published. | E26: Draft blog exists. | F26: Passed | H26: TrungDN | I26: Passed | K26: KhoaPA | L26: Passed | N26: TrungDN
A27: TC4512 | B27: Blog action error handling | C27: 1. Simulate API errors for approve/reject/publish/delete/updateStatus. | D27: Action error banner and toast appear; UI remains operable. | E27: Error simulation available. | F27: Passed | H27: TrungDN | I27: Passed | K27: KhoaPA | L27: Passed | N27: TrungDN

Sheet Feature 2
A2: Feature | B2: <Feature Name2> | R2: Passed
A3: Test requirement | B3: <Brief description about requirements which are tested in this sheet> | R3: Failed
A4: Number of TCs | B4: =COUNTA(A12:A998) -> 6 | R4: Pending
A5: Testing Round | B5: Passed | C5: Failed | D5: Pending | E5: N/A | R5: N/A
A6: Round 1 | B6: =COUNTIF($F10:$F996,B5) -> 0 | C6: =COUNTIF($F10:$F996,C5) -> 0 | D6: =COUNTIF($F10:$F996,D5) -> 5 | E6: =COUNTIF($F10:$F996,E5) -> 0
A7: Round 2 | B7: =COUNTIF($F10:$F996,B5) -> 0 | C7: =COUNTIF($F10:$F996,C5) -> 0 | D7: =COUNTIF($F10:$F996,D5) -> 5 | E7: =COUNTIF($F10:$F996,E5) -> 0
A8: Round 3 | B8: =COUNTIF($F10:$F996,B5) -> 0 | C8: =COUNTIF($F10:$F996,C5) -> 0 | D8: =COUNTIF($F10:$F996,D5) -> 5 | E8: =COUNTIF($F10:$F996,E5) -> 0
A10: Test Case ID | B10: Test Case Description | C10: Test Case Procedure | D10: Expected Results | E10: Pre-conditions | F10: Round 1 | G10: Test date | H10: Tester | I10: Round 2 | J10: Test date | K10: Tester | L10: Round 3 | M10: Test date | N10: Tester | O10: Note
A11: Function D
A12: <ID1> | B12: <Brief description of this case: what is tested?> Ex: Test viewing "Company" form. | C12: <Describe steps to perform this case> Ex: 1. Login the system with Manager role. 2. Click "Company" tab in the left menu. | D12: <Describe results which meet customer's requirement> Ex: The "Company" view form is displayed with the folowing informations: - Company name - Company address - Phone - Fax | E12: <List all test cases or conditions that must be done before performing this case> | F12: Pending | I12: Pending | L12: Pending
A13: <ID2> | B13: <Test case 2> | F13: Pending | I13: Pending | L13: Pending
A14: <ID3> | B14: <Test case 3> | F14: Pending | I14: Pending | L14: Pending
A15: Function E
A16: <ID4> | B16: <Test case 4> | F16: Pending | I16: Pending | L16: Pending
A17: <ID5> | B17: <Test case 5> | F17: Pending | I17: Pending | L17: Pending
